<?xml version="1.0" encoding="utf-8"?>
<SoundBanksInfo Platform="Windows" BasePlatform="Windows" SchemaVersion="12" SoundbankVersion="140">
	<RootPaths>
		<ProjectRoot>C:\Users\fcbal\Documents\GitHub\WwiseAudioProject\AdventureGame\</ProjectRoot>
		<SourceFilesRoot>C:\Users\fcbal\Documents\GitHub\WwiseAudioProject\AdventureGame\.cache\Windows\</SourceFilesRoot>
		<SoundBanksRoot>C:\Users\fcbal\Documents\GitHub\WwiseAudioProject\WwiseAdventureGame\WwiseAdventureGame_Data\StreamingAssets\Audio\GeneratedSoundBanks\Windows\</SoundBanksRoot>
		<ExternalSourcesInputFile></ExternalSourcesInputFile>
		<ExternalSourcesOutputRoot>C:\Users\fcbal\Documents\GitHub\WwiseAudioProject\AdventureGame\GeneratedSoundBanks\Windows</ExternalSourcesOutputRoot>
	</RootPaths>
	<DialogueEvents/>
	<StreamedFiles/>
	<MediaFilesNotInAnyBank/>
	<SoundBanks>
		<SoundBank Id="133642231" Language="SFX" Hash="2921926488">
			<ObjectPath>\SoundBanks\Default Work Unit\General</ObjectPath>
			<ShortName>General</ShortName>
			<Path>General.bnk</Path>
			<IncludedEvents>
				<Event Id="4254124015" Name="Destruction_Container" ObjectPath="\Events\Default Work Unit\Destruction_Container">
					<IncludedMemoryFiles>
						<File Id="44139011" Language="SFX">
							<ShortName>Destruction\BAS_Crate_Destroy_04.wav</ShortName>
							<Path>SFX\Destruction\BAS_Crate_Destroy_04_10C4C929.wem</Path>
						</File>
						<File Id="129434280" Language="SFX">
							<ShortName>Destruction\BAS_Crate_Destroy_01.wav</ShortName>
							<Path>SFX\Destruction\BAS_Crate_Destroy_01_10C4C929.wem</Path>
						</File>
						<File Id="273344923" Language="SFX">
							<ShortName>Destruction\BAS_Crate_Destroy_03.wav</ShortName>
							<Path>SFX\Destruction\BAS_Crate_Destroy_03_10C4C929.wem</Path>
						</File>
						<File Id="519586475" Language="SFX">
							<ShortName>Destruction\BAS_Crate_Destroy_06.wav</ShortName>
							<Path>SFX\Destruction\BAS_Crate_Destroy_06_10C4C929.wem</Path>
						</File>
						<File Id="635677513" Language="SFX">
							<ShortName>Destruction\BAS_Crate_Destroy_02.wav</ShortName>
							<Path>SFX\Destruction\BAS_Crate_Destroy_02_10C4C929.wem</Path>
						</File>
						<File Id="795583947" Language="SFX">
							<ShortName>Destruction\BAS_Crate_Destroy_05.wav</ShortName>
							<Path>SFX\Destruction\BAS_Crate_Destroy_05_10C4C929.wem</Path>
						</File>
					</IncludedMemoryFiles>
				</Event>
				<Event Id="3741135221" Name="Music_Region" ObjectPath="\Events\Default Work Unit\Music_Region">
					<IncludedMemoryFiles>
						<File Id="2294066" Language="SFX">
							<ShortName>Music\Explore\Woodlands_Day_120BPM_4_4_L8M_P0.wav</ShortName>
							<Path>SFX\Music\Explore\Woodlands_Day_120BPM_4_4_L8M_P0_295D3E20.wem</Path>
						</File>
						<File Id="425573456" Language="SFX">
							<ShortName>Music\Explore\Nowhere_120BPM_4_4_L8M_P0.wav</ShortName>
							<Path>SFX\Music\Explore\Nowhere_120BPM_4_4_L8M_P0_46880729.wem</Path>
						</File>
						<File Id="443672102" Language="SFX">
							<ShortName>Music\Explore\Woodlands_Night_120BPM_4_4_L8M_P1M.wav</ShortName>
							<Path>SFX\Music\Explore\Woodlands_Night_120BPM_4_4_L8M_P1M_169D1EF8.wem</Path>
						</File>
						<File Id="679507772" Language="SFX">
							<ShortName>Music\Explore\Cave_Silent_WwizardHouse_120BPM_L8M_P0.wav</ShortName>
							<Path>SFX\Music\Explore\Cave_Silent_WwizardHouse_120BPM_L8M_P0_46AE9E07.wem</Path>
						</File>
						<File Id="704765242" Language="SFX">
							<ShortName>Music\Explore\Dungeon_120BPM_4_4_L8M_P1M.wav</ShortName>
							<Path>SFX\Music\Explore\Dungeon_120BPM_4_4_L8M_P1M_A6AA60CA.wem</Path>
						</File>
						<File Id="829177987" Language="SFX">
							<ShortName>Music\Explore\Village_120BPM_4_4_L8M_P1M.wav</ShortName>
							<Path>SFX\Music\Explore\Village_120BPM_4_4_L8M_P1M_491F58E2.wem</Path>
						</File>
						<File Id="965643848" Language="SFX">
							<ShortName>Music\Explore\Desert_120BPM_4_4_L8M_P0.wav</ShortName>
							<Path>SFX\Music\Explore\Desert_120BPM_4_4_L8M_P0_E746A6C8.wem</Path>
						</File>
					</IncludedMemoryFiles>
					<DefaultSwitchValue>{67D03A08-4A6F-4CDE-8E3E-E2364F7F33B0}</DefaultSwitchValue>
					<SwitchContainers>
						<SwitchContainer SwitchValue="{67D03A08-4A6F-4CDE-8E3E-E2364F7F33B0}">
							<DefaultSwitchValue>{12B8D30A-EE92-4CBB-A492-4914DF46DB52}</DefaultSwitchValue>
							<Children>
								<SwitchContainer SwitchValue="{12B8D30A-EE92-4CBB-A492-4914DF46DB52}">
									<Media>
										<File Id="2294066"/>
									</Media>
								</SwitchContainer>
								<SwitchContainer SwitchValue="{23EEB13D-026D-43C2-A3DA-96B33F5888AE}">
									<Media>
										<File Id="443672102"/>
									</Media>
								</SwitchContainer>
							</Children>
						</SwitchContainer>
						<SwitchContainer SwitchValue="{0C2F6D1C-FA40-42FB-9F9A-7CDAB9AC23E7}">
							<Media>
								<File Id="829177987"/>
							</Media>
						</SwitchContainer>
						<SwitchContainer SwitchValue="{4124A71E-9192-4796-A94E-4195D16349C3}">
							<Media>
								<File Id="679507772"/>
							</Media>
						</SwitchContainer>
						<SwitchContainer SwitchValue="{61BDAE3A-0243-4F48-A840-D64D9589B424}">
							<Media>
								<File Id="425573456"/>
							</Media>
						</SwitchContainer>
						<SwitchContainer SwitchValue="{AD69625B-0DF9-4CD1-8912-47D4AFA2C60D}">
							<Media>
								<File Id="679507772"/>
							</Media>
						</SwitchContainer>
						<SwitchContainer SwitchValue="{AA980662-8B5B-4247-B0CD-4C1BEB1B50DD}">
							<Media>
								<File Id="965643848"/>
							</Media>
						</SwitchContainer>
						<SwitchContainer SwitchValue="{1083B2A5-4AAD-4FC3-B245-6EC2E345567F}">
							<Media>
								<File Id="704765242"/>
							</Media>
						</SwitchContainer>
						<SwitchContainer SwitchValue="{399C57E6-3EB3-4342-A2D9-58F9298F6B08}">
							<Media>
								<File Id="679507772"/>
							</Media>
						</SwitchContainer>
					</SwitchContainers>
				</Event>
				<Event Id="2453392179" Name="Player_Footstep" ObjectPath="\Events\Default Work Unit\Player_Footstep">
					<IncludedMemoryFiles>
						<File Id="25007798" Language="SFX">
							<ShortName>Footsteps\Run\Grass\BAS_Player_Footstep_grass_run_06.wav</ShortName>
							<Path>SFX\Footsteps\Run\Grass\BAS_Player_Footstep_grass_run_06_10C4C929.wem</Path>
						</File>
						<File Id="43324162" Language="SFX">
							<ShortName>Footsteps\Run\Water\BAS_Player_Footstep_water_run_06.wav</ShortName>
							<Path>SFX\Footsteps\Run\Water\BAS_Player_Footstep_water_run_06_10C4C929.wem</Path>
						</File>
						<File Id="45000150" Language="SFX">
							<ShortName>Footsteps\Run\Stone\BAS_Player_Footstep_stone_run_06.wav</ShortName>
							<Path>SFX\Footsteps\Run\Stone\BAS_Player_Footstep_stone_run_06_10C4C929.wem</Path>
						</File>
						<File Id="46106826" Language="SFX">
							<ShortName>Footsteps\Run\Wood\BAS_Player_Footstep_wood_run_02.wav</ShortName>
							<Path>SFX\Footsteps\Run\Wood\BAS_Player_Footstep_wood_run_02_10C4C929.wem</Path>
						</File>
						<File Id="60630466" Language="SFX">
							<ShortName>Footsteps\Walk\Water\BAS_Player_Footstep_water_walk_03.wav</ShortName>
							<Path>SFX\Footsteps\Walk\Water\BAS_Player_Footstep_water_walk_03_10C4C929.wem</Path>
						</File>
						<File Id="68308165" Language="SFX">
							<ShortName>Footsteps\Run\Grass\BAS_Player_Footstep_grass_run_02.wav</ShortName>
							<Path>SFX\Footsteps\Run\Grass\BAS_Player_Footstep_grass_run_02_10C4C929.wem</Path>
						</File>
						<File Id="83312605" Language="SFX">
							<ShortName>Footsteps\Walk\Rubble\BAS_Player_Footstep_rubble_walk_05.wav</ShortName>
							<Path>SFX\Footsteps\Walk\Rubble\BAS_Player_Footstep_rubble_walk_05_10C4C929.wem</Path>
						</File>
						<File Id="86339568" Language="SFX">
							<ShortName>Footsteps\Run\Sand\BAS_Player_Footstep_sand_run_01.wav</ShortName>
							<Path>SFX\Footsteps\Run\Sand\BAS_Player_Footstep_sand_run_01_10C4C929.wem</Path>
						</File>
						<File Id="105517932" Language="SFX">
							<ShortName>Footsteps\Walk\Dirt\BAS_Player_Footstep_dirt_walk_01.wav</ShortName>
							<Path>SFX\Footsteps\Walk\Dirt\BAS_Player_Footstep_dirt_walk_01_10C4C929.wem</Path>
						</File>
						<File Id="118964264" Language="SFX">
							<ShortName>Footsteps\Run\Dirt\BAS_Player_Footstep_dirt_run_03.wav</ShortName>
							<Path>SFX\Footsteps\Run\Dirt\BAS_Player_Footstep_dirt_run_03_10C4C929.wem</Path>
						</File>
						<File Id="119306444" Language="SFX">
							<ShortName>Footsteps\Walk\Wood\BAS_Player_Footstep_wood_walk_04.wav</ShortName>
							<Path>SFX\Footsteps\Walk\Wood\BAS_Player_Footstep_wood_walk_04_10C4C929.wem</Path>
						</File>
						<File Id="128137016" Language="SFX">
							<ShortName>Footsteps\Walk\Dirt\BAS_Player_Footstep_dirt_walk_02.wav</ShortName>
							<Path>SFX\Footsteps\Walk\Dirt\BAS_Player_Footstep_dirt_walk_02_10C4C929.wem</Path>
						</File>
						<File Id="132029450" Language="SFX">
							<ShortName>Footsteps\Run\Sand\BAS_Player_Footstep_sand_run_04.wav</ShortName>
							<Path>SFX\Footsteps\Run\Sand\BAS_Player_Footstep_sand_run_04_10C4C929.wem</Path>
						</File>
						<File Id="134813006" Language="SFX">
							<ShortName>Footsteps\Run\Wood\BAS_Player_Footstep_wood_run_04.wav</ShortName>
							<Path>SFX\Footsteps\Run\Wood\BAS_Player_Footstep_wood_run_04_10C4C929.wem</Path>
						</File>
						<File Id="137964504" Language="SFX">
							<ShortName>Footsteps\Walk\Water\BAS_Player_Footstep_water_walk_04.wav</ShortName>
							<Path>SFX\Footsteps\Walk\Water\BAS_Player_Footstep_water_walk_04_10C4C929.wem</Path>
						</File>
						<File Id="139623825" Language="SFX">
							<ShortName>Footsteps\Walk\Grass\BAS_Player_Footstep_grass_walk_06.wav</ShortName>
							<Path>SFX\Footsteps\Walk\Grass\BAS_Player_Footstep_grass_walk_06_10C4C929.wem</Path>
						</File>
						<File Id="148930992" Language="SFX">
							<ShortName>Footsteps\Run\Grass\BAS_Player_Footstep_grass_run_01.wav</ShortName>
							<Path>SFX\Footsteps\Run\Grass\BAS_Player_Footstep_grass_run_01_10C4C929.wem</Path>
						</File>
						<File Id="149169872" Language="SFX">
							<ShortName>Footsteps\Walk\Dirt\BAS_Player_Footstep_dirt_walk_06.wav</ShortName>
							<Path>SFX\Footsteps\Walk\Dirt\BAS_Player_Footstep_dirt_walk_06_10C4C929.wem</Path>
						</File>
						<File Id="200617368" Language="SFX">
							<ShortName>Footsteps\Walk\Rubble\BAS_Player_Footstep_rubble_walk_03.wav</ShortName>
							<Path>SFX\Footsteps\Walk\Rubble\BAS_Player_Footstep_rubble_walk_03_10C4C929.wem</Path>
						</File>
						<File Id="212355571" Language="SFX">
							<ShortName>Footsteps\Run\Water\BAS_Player_Footstep_water_run_02.wav</ShortName>
							<Path>SFX\Footsteps\Run\Water\BAS_Player_Footstep_water_run_02_10C4C929.wem</Path>
						</File>
						<File Id="213024346" Language="SFX">
							<ShortName>Footsteps\Walk\Dirt\BAS_Player_Footstep_dirt_walk_03.wav</ShortName>
							<Path>SFX\Footsteps\Walk\Dirt\BAS_Player_Footstep_dirt_walk_03_10C4C929.wem</Path>
						</File>
						<File Id="229455186" Language="SFX">
							<ShortName>Footsteps\Run\Rubble\BAS_Player_Footstep_rubble_run_02.wav</ShortName>
							<Path>SFX\Footsteps\Run\Rubble\BAS_Player_Footstep_rubble_run_02_10C4C929.wem</Path>
						</File>
						<File Id="231965061" Language="SFX">
							<ShortName>Footsteps\Run\Grass\BAS_Player_Footstep_grass_run_05.wav</ShortName>
							<Path>SFX\Footsteps\Run\Grass\BAS_Player_Footstep_grass_run_05_10C4C929.wem</Path>
						</File>
						<File Id="260592815" Language="SFX">
							<ShortName>Footsteps\Walk\Dirt\BAS_Player_Footstep_dirt_walk_04.wav</ShortName>
							<Path>SFX\Footsteps\Walk\Dirt\BAS_Player_Footstep_dirt_walk_04_10C4C929.wem</Path>
						</File>
						<File Id="263890707" Language="SFX">
							<ShortName>Footsteps\Walk\Grass\BAS_Player_Footstep_grass_walk_03.wav</ShortName>
							<Path>SFX\Footsteps\Walk\Grass\BAS_Player_Footstep_grass_walk_03_10C4C929.wem</Path>
						</File>
						<File Id="264420771" Language="SFX">
							<ShortName>Footsteps\Walk\Sand\BAS_Player_Footstep_sand_walk_06.wav</ShortName>
							<Path>SFX\Footsteps\Walk\Sand\BAS_Player_Footstep_sand_walk_06_10C4C929.wem</Path>
						</File>
						<File Id="269374664" Language="SFX">
							<ShortName>Footsteps\Walk\Sand\BAS_Player_Footstep_sand_walk_05.wav</ShortName>
							<Path>SFX\Footsteps\Walk\Sand\BAS_Player_Footstep_sand_walk_05_10C4C929.wem</Path>
						</File>
						<File Id="271452971" Language="SFX">
							<ShortName>Footsteps\Run\Sand\BAS_Player_Footstep_sand_run_03.wav</ShortName>
							<Path>SFX\Footsteps\Run\Sand\BAS_Player_Footstep_sand_run_03_10C4C929.wem</Path>
						</File>
						<File Id="274060594" Language="SFX">
							<ShortName>Footsteps\Run\Rubble\BAS_Player_Footstep_rubble_run_01.wav</ShortName>
							<Path>SFX\Footsteps\Run\Rubble\BAS_Player_Footstep_rubble_run_01_10C4C929.wem</Path>
						</File>
						<File Id="284223424" Language="SFX">
							<ShortName>Footsteps\Run\Stone\BAS_Player_Footstep_stone_run_03.wav</ShortName>
							<Path>SFX\Footsteps\Run\Stone\BAS_Player_Footstep_stone_run_03_10C4C929.wem</Path>
						</File>
						<File Id="287885192" Language="SFX">
							<ShortName>Footsteps\Walk\Rubble\BAS_Player_Footstep_rubble_walk_04.wav</ShortName>
							<Path>SFX\Footsteps\Walk\Rubble\BAS_Player_Footstep_rubble_walk_04_10C4C929.wem</Path>
						</File>
						<File Id="288736737" Language="SFX">
							<ShortName>Footsteps\Walk\Grass\BAS_Player_Footstep_grass_walk_02.wav</ShortName>
							<Path>SFX\Footsteps\Walk\Grass\BAS_Player_Footstep_grass_walk_02_10C4C929.wem</Path>
						</File>
						<File Id="289083996" Language="SFX">
							<ShortName>Footsteps\Walk\Stone\BAS_Player_Footstep_stone_walk_01.wav</ShortName>
							<Path>SFX\Footsteps\Walk\Stone\BAS_Player_Footstep_stone_walk_01_10C4C929.wem</Path>
						</File>
						<File Id="313562469" Language="SFX">
							<ShortName>Footsteps\Walk\Wood\BAS_Player_Footstep_wood_walk_02.wav</ShortName>
							<Path>SFX\Footsteps\Walk\Wood\BAS_Player_Footstep_wood_walk_02_10C4C929.wem</Path>
						</File>
						<File Id="317704190" Language="SFX">
							<ShortName>Footsteps\Walk\Grass\BAS_Player_Footstep_grass_walk_01.wav</ShortName>
							<Path>SFX\Footsteps\Walk\Grass\BAS_Player_Footstep_grass_walk_01_10C4C929.wem</Path>
						</File>
						<File Id="320599554" Language="SFX">
							<ShortName>Footsteps\Run\Sand\BAS_Player_Footstep_sand_run_06.wav</ShortName>
							<Path>SFX\Footsteps\Run\Sand\BAS_Player_Footstep_sand_run_06_10C4C929.wem</Path>
						</File>
						<File Id="342450304" Language="SFX">
							<ShortName>Footsteps\Run\Dirt\BAS_Player_Footstep_dirt_run_05.wav</ShortName>
							<Path>SFX\Footsteps\Run\Dirt\BAS_Player_Footstep_dirt_run_05_10C4C929.wem</Path>
						</File>
						<File Id="381610979" Language="SFX">
							<ShortName>Footsteps\Run\Wood\BAS_Player_Footstep_wood_run_06.wav</ShortName>
							<Path>SFX\Footsteps\Run\Wood\BAS_Player_Footstep_wood_run_06_10C4C929.wem</Path>
						</File>
						<File Id="388336872" Language="SFX">
							<ShortName>Footsteps\Walk\Stone\BAS_Player_Footstep_stone_walk_04.wav</ShortName>
							<Path>SFX\Footsteps\Walk\Stone\BAS_Player_Footstep_stone_walk_04_10C4C929.wem</Path>
						</File>
						<File Id="391077158" Language="SFX">
							<ShortName>Footsteps\Walk\Dirt\BAS_Player_Footstep_dirt_walk_05.wav</ShortName>
							<Path>SFX\Footsteps\Walk\Dirt\BAS_Player_Footstep_dirt_walk_05_10C4C929.wem</Path>
						</File>
						<File Id="407173061" Language="SFX">
							<ShortName>Footsteps\Run\Grass\BAS_Player_Footstep_grass_run_04.wav</ShortName>
							<Path>SFX\Footsteps\Run\Grass\BAS_Player_Footstep_grass_run_04_10C4C929.wem</Path>
						</File>
						<File Id="427170479" Language="SFX">
							<ShortName>Footsteps\Run\Wood\BAS_Player_Footstep_wood_run_03.wav</ShortName>
							<Path>SFX\Footsteps\Run\Wood\BAS_Player_Footstep_wood_run_03_10C4C929.wem</Path>
						</File>
						<File Id="433106662" Language="SFX">
							<ShortName>Footsteps\Walk\Wood\BAS_Player_Footstep_wood_walk_01.wav</ShortName>
							<Path>SFX\Footsteps\Walk\Wood\BAS_Player_Footstep_wood_walk_01_10C4C929.wem</Path>
						</File>
						<File Id="443004522" Language="SFX">
							<ShortName>Footsteps\Run\Water\BAS_Player_Footstep_water_run_03.wav</ShortName>
							<Path>SFX\Footsteps\Run\Water\BAS_Player_Footstep_water_run_03_10C4C929.wem</Path>
						</File>
						<File Id="451453123" Language="SFX">
							<ShortName>Footsteps\Run\Rubble\BAS_Player_Footstep_rubble_run_05.wav</ShortName>
							<Path>SFX\Footsteps\Run\Rubble\BAS_Player_Footstep_rubble_run_05_10C4C929.wem</Path>
						</File>
						<File Id="496634122" Language="SFX">
							<ShortName>Footsteps\Run\Stone\BAS_Player_Footstep_stone_run_01.wav</ShortName>
							<Path>SFX\Footsteps\Run\Stone\BAS_Player_Footstep_stone_run_01_10C4C929.wem</Path>
						</File>
						<File Id="526136462" Language="SFX">
							<ShortName>Footsteps\Walk\Water\BAS_Player_Footstep_water_walk_02.wav</ShortName>
							<Path>SFX\Footsteps\Walk\Water\BAS_Player_Footstep_water_walk_02_10C4C929.wem</Path>
						</File>
						<File Id="545654536" Language="SFX">
							<ShortName>Footsteps\Run\Dirt\BAS_Player_Footstep_dirt_run_02.wav</ShortName>
							<Path>SFX\Footsteps\Run\Dirt\BAS_Player_Footstep_dirt_run_02_10C4C929.wem</Path>
						</File>
						<File Id="557396045" Language="SFX">
							<ShortName>Footsteps\Run\Sand\BAS_Player_Footstep_sand_run_02.wav</ShortName>
							<Path>SFX\Footsteps\Run\Sand\BAS_Player_Footstep_sand_run_02_10C4C929.wem</Path>
						</File>
						<File Id="572464380" Language="SFX">
							<ShortName>Footsteps\Walk\Grass\BAS_Player_Footstep_grass_walk_04.wav</ShortName>
							<Path>SFX\Footsteps\Walk\Grass\BAS_Player_Footstep_grass_walk_04_10C4C929.wem</Path>
						</File>
						<File Id="574018462" Language="SFX">
							<ShortName>Footsteps\Run\Dirt\BAS_Player_Footstep_dirt_run_01.wav</ShortName>
							<Path>SFX\Footsteps\Run\Dirt\BAS_Player_Footstep_dirt_run_01_10C4C929.wem</Path>
						</File>
						<File Id="576641613" Language="SFX">
							<ShortName>Footsteps\Walk\Water\BAS_Player_Footstep_water_walk_01.wav</ShortName>
							<Path>SFX\Footsteps\Walk\Water\BAS_Player_Footstep_water_walk_01_10C4C929.wem</Path>
						</File>
						<File Id="576924454" Language="SFX">
							<ShortName>Footsteps\Walk\Grass\BAS_Player_Footstep_grass_walk_05.wav</ShortName>
							<Path>SFX\Footsteps\Walk\Grass\BAS_Player_Footstep_grass_walk_05_10C4C929.wem</Path>
						</File>
						<File Id="590730046" Language="SFX">
							<ShortName>Footsteps\Run\Wood\BAS_Player_Footstep_wood_run_01.wav</ShortName>
							<Path>SFX\Footsteps\Run\Wood\BAS_Player_Footstep_wood_run_01_10C4C929.wem</Path>
						</File>
						<File Id="593030260" Language="SFX">
							<ShortName>Footsteps\Run\Wood\BAS_Player_Footstep_wood_run_05.wav</ShortName>
							<Path>SFX\Footsteps\Run\Wood\BAS_Player_Footstep_wood_run_05_10C4C929.wem</Path>
						</File>
						<File Id="612923756" Language="SFX">
							<ShortName>Footsteps\Walk\Water\BAS_Player_Footstep_water_walk_06.wav</ShortName>
							<Path>SFX\Footsteps\Walk\Water\BAS_Player_Footstep_water_walk_06_10C4C929.wem</Path>
						</File>
						<File Id="614158301" Language="SFX">
							<ShortName>Footsteps\Run\Stone\BAS_Player_Footstep_stone_run_05.wav</ShortName>
							<Path>SFX\Footsteps\Run\Stone\BAS_Player_Footstep_stone_run_05_10C4C929.wem</Path>
						</File>
						<File Id="654137681" Language="SFX">
							<ShortName>Footsteps\Walk\Wood\BAS_Player_Footstep_wood_walk_05.wav</ShortName>
							<Path>SFX\Footsteps\Walk\Wood\BAS_Player_Footstep_wood_walk_05_10C4C929.wem</Path>
						</File>
						<File Id="689274655" Language="SFX">
							<ShortName>Footsteps\Run\Water\BAS_Player_Footstep_water_run_05.wav</ShortName>
							<Path>SFX\Footsteps\Run\Water\BAS_Player_Footstep_water_run_05_10C4C929.wem</Path>
						</File>
						<File Id="697470634" Language="SFX">
							<ShortName>Footsteps\Run\Dirt\BAS_Player_Footstep_dirt_run_06.wav</ShortName>
							<Path>SFX\Footsteps\Run\Dirt\BAS_Player_Footstep_dirt_run_06_10C4C929.wem</Path>
						</File>
						<File Id="739832514" Language="SFX">
							<ShortName>Footsteps\Run\Water\BAS_Player_Footstep_water_run_01.wav</ShortName>
							<Path>SFX\Footsteps\Run\Water\BAS_Player_Footstep_water_run_01_10C4C929.wem</Path>
						</File>
						<File Id="741324826" Language="SFX">
							<ShortName>Footsteps\Walk\Sand\BAS_Player_Footstep_sand_walk_01.wav</ShortName>
							<Path>SFX\Footsteps\Walk\Sand\BAS_Player_Footstep_sand_walk_01_10C4C929.wem</Path>
						</File>
						<File Id="755095991" Language="SFX">
							<ShortName>Footsteps\Walk\Rubble\BAS_Player_Footstep_rubble_walk_02.wav</ShortName>
							<Path>SFX\Footsteps\Walk\Rubble\BAS_Player_Footstep_rubble_walk_02_10C4C929.wem</Path>
						</File>
						<File Id="758074194" Language="SFX">
							<ShortName>Footsteps\Run\Grass\BAS_Player_Footstep_grass_run_03.wav</ShortName>
							<Path>SFX\Footsteps\Run\Grass\BAS_Player_Footstep_grass_run_03_10C4C929.wem</Path>
						</File>
						<File Id="762876477" Language="SFX">
							<ShortName>Footsteps\Walk\Sand\BAS_Player_Footstep_sand_walk_03.wav</ShortName>
							<Path>SFX\Footsteps\Walk\Sand\BAS_Player_Footstep_sand_walk_03_10C4C929.wem</Path>
						</File>
						<File Id="765729031" Language="SFX">
							<ShortName>Footsteps\Walk\Stone\BAS_Player_Footstep_stone_walk_06.wav</ShortName>
							<Path>SFX\Footsteps\Walk\Stone\BAS_Player_Footstep_stone_walk_06_10C4C929.wem</Path>
						</File>
						<File Id="773371363" Language="SFX">
							<ShortName>Footsteps\Walk\Wood\BAS_Player_Footstep_wood_walk_06.wav</ShortName>
							<Path>SFX\Footsteps\Walk\Wood\BAS_Player_Footstep_wood_walk_06_10C4C929.wem</Path>
						</File>
						<File Id="822535565" Language="SFX">
							<ShortName>Footsteps\Run\Dirt\BAS_Player_Footstep_dirt_run_04.wav</ShortName>
							<Path>SFX\Footsteps\Run\Dirt\BAS_Player_Footstep_dirt_run_04_10C4C929.wem</Path>
						</File>
						<File Id="830613387" Language="SFX">
							<ShortName>Footsteps\Run\Sand\BAS_Player_Footstep_sand_run_05.wav</ShortName>
							<Path>SFX\Footsteps\Run\Sand\BAS_Player_Footstep_sand_run_05_10C4C929.wem</Path>
						</File>
						<File Id="871507814" Language="SFX">
							<ShortName>Footsteps\Run\Rubble\BAS_Player_Footstep_rubble_run_04.wav</ShortName>
							<Path>SFX\Footsteps\Run\Rubble\BAS_Player_Footstep_rubble_run_04_10C4C929.wem</Path>
						</File>
						<File Id="885548314" Language="SFX">
							<ShortName>Footsteps\Walk\Sand\BAS_Player_Footstep_sand_walk_02.wav</ShortName>
							<Path>SFX\Footsteps\Walk\Sand\BAS_Player_Footstep_sand_walk_02_10C4C929.wem</Path>
						</File>
						<File Id="931676924" Language="SFX">
							<ShortName>Footsteps\Walk\Rubble\BAS_Player_Footstep_rubble_walk_06.wav</ShortName>
							<Path>SFX\Footsteps\Walk\Rubble\BAS_Player_Footstep_rubble_walk_06_10C4C929.wem</Path>
						</File>
						<File Id="955500942" Language="SFX">
							<ShortName>Footsteps\Run\Stone\BAS_Player_Footstep_stone_run_02.wav</ShortName>
							<Path>SFX\Footsteps\Run\Stone\BAS_Player_Footstep_stone_run_02_10C4C929.wem</Path>
						</File>
						<File Id="956762804" Language="SFX">
							<ShortName>Footsteps\Walk\Sand\BAS_Player_Footstep_sand_walk_04.wav</ShortName>
							<Path>SFX\Footsteps\Walk\Sand\BAS_Player_Footstep_sand_walk_04_10C4C929.wem</Path>
						</File>
						<File Id="960018224" Language="SFX">
							<ShortName>Footsteps\Run\Water\BAS_Player_Footstep_water_run_04.wav</ShortName>
							<Path>SFX\Footsteps\Run\Water\BAS_Player_Footstep_water_run_04_10C4C929.wem</Path>
						</File>
						<File Id="963554935" Language="SFX">
							<ShortName>Footsteps\Run\Rubble\BAS_Player_Footstep_rubble_run_03.wav</ShortName>
							<Path>SFX\Footsteps\Run\Rubble\BAS_Player_Footstep_rubble_run_03_10C4C929.wem</Path>
						</File>
						<File Id="964417384" Language="SFX">
							<ShortName>Footsteps\Walk\Stone\BAS_Player_Footstep_stone_walk_03.wav</ShortName>
							<Path>SFX\Footsteps\Walk\Stone\BAS_Player_Footstep_stone_walk_03_10C4C929.wem</Path>
						</File>
						<File Id="996996158" Language="SFX">
							<ShortName>Footsteps\Walk\Stone\BAS_Player_Footstep_stone_walk_02.wav</ShortName>
							<Path>SFX\Footsteps\Walk\Stone\BAS_Player_Footstep_stone_walk_02_10C4C929.wem</Path>
						</File>
						<File Id="1013155879" Language="SFX">
							<ShortName>Footsteps\Run\Stone\BAS_Player_Footstep_stone_run_04.wav</ShortName>
							<Path>SFX\Footsteps\Run\Stone\BAS_Player_Footstep_stone_run_04_10C4C929.wem</Path>
						</File>
						<File Id="1022859956" Language="SFX">
							<ShortName>Footsteps\Run\Rubble\BAS_Player_Footstep_rubble_run_06.wav</ShortName>
							<Path>SFX\Footsteps\Run\Rubble\BAS_Player_Footstep_rubble_run_06_10C4C929.wem</Path>
						</File>
						<File Id="1023464345" Language="SFX">
							<ShortName>Footsteps\Walk\Wood\BAS_Player_Footstep_wood_walk_03.wav</ShortName>
							<Path>SFX\Footsteps\Walk\Wood\BAS_Player_Footstep_wood_walk_03_10C4C929.wem</Path>
						</File>
						<File Id="1062391457" Language="SFX">
							<ShortName>Footsteps\Walk\Water\BAS_Player_Footstep_water_walk_05.wav</ShortName>
							<Path>SFX\Footsteps\Walk\Water\BAS_Player_Footstep_water_walk_05_10C4C929.wem</Path>
						</File>
						<File Id="1071381212" Language="SFX">
							<ShortName>Footsteps\Walk\Stone\BAS_Player_Footstep_stone_walk_05.wav</ShortName>
							<Path>SFX\Footsteps\Walk\Stone\BAS_Player_Footstep_stone_walk_05_10C4C929.wem</Path>
						</File>
					</IncludedMemoryFiles>
					<DefaultSwitchValue>{7C08ADDB-8F7F-4FA0-8899-A06126EC92CD}</DefaultSwitchValue>
					<SwitchContainers>
						<SwitchContainer SwitchValue="{495D2402-2BA5-491C-AB8F-A1A2D1E192F5}">
							<DefaultSwitchValue>{B5A62B1A-4136-49D8-93E9-13FF3EF16C12}</DefaultSwitchValue>
							<Children>
								<SwitchContainer SwitchValue="{A3611407-73C1-43BB-93FA-F956D69790E9}">
									<Media>
										<File Id="229455186"/>
										<File Id="274060594"/>
										<File Id="451453123"/>
										<File Id="871507814"/>
										<File Id="963554935"/>
										<File Id="1022859956"/>
									</Media>
								</SwitchContainer>
								<SwitchContainer SwitchValue="{8BFF390B-ECB3-4F13-A870-8F92D48659CF}">
									<Media>
										<File Id="118964264"/>
										<File Id="342450304"/>
										<File Id="545654536"/>
										<File Id="574018462"/>
										<File Id="697470634"/>
										<File Id="822535565"/>
									</Media>
								</SwitchContainer>
								<SwitchContainer SwitchValue="{2FFB930C-2D31-4CFC-9B3F-5E2F700C60F5}">
									<Media>
										<File Id="43324162"/>
										<File Id="212355571"/>
										<File Id="443004522"/>
										<File Id="689274655"/>
										<File Id="739832514"/>
										<File Id="960018224"/>
									</Media>
								</SwitchContainer>
								<SwitchContainer SwitchValue="{3770F718-700F-4BC9-A5CE-8F4BFDF7A781}">
									<Media>
										<File Id="118964264"/>
										<File Id="342450304"/>
										<File Id="545654536"/>
										<File Id="574018462"/>
										<File Id="697470634"/>
										<File Id="822535565"/>
									</Media>
								</SwitchContainer>
								<SwitchContainer SwitchValue="{B5A62B1A-4136-49D8-93E9-13FF3EF16C12}">
									<Media>
										<File Id="118964264"/>
										<File Id="342450304"/>
										<File Id="545654536"/>
										<File Id="574018462"/>
										<File Id="697470634"/>
										<File Id="822535565"/>
									</Media>
								</SwitchContainer>
								<SwitchContainer SwitchValue="{17E6DB35-2703-499D-B807-D0C75D81C2C1}">
									<Media>
										<File Id="118964264"/>
										<File Id="342450304"/>
										<File Id="545654536"/>
										<File Id="574018462"/>
										<File Id="697470634"/>
										<File Id="822535565"/>
									</Media>
								</SwitchContainer>
								<SwitchContainer SwitchValue="{FA3E484A-5996-4A28-BFA4-FF7EB6717409}">
									<Media>
										<File Id="118964264"/>
										<File Id="342450304"/>
										<File Id="545654536"/>
										<File Id="574018462"/>
										<File Id="697470634"/>
										<File Id="822535565"/>
									</Media>
								</SwitchContainer>
								<SwitchContainer SwitchValue="{32668058-5BF8-40EE-9E9C-2F4E2EE0A199}">
									<Media>
										<File Id="25007798"/>
										<File Id="68308165"/>
										<File Id="148930992"/>
										<File Id="231965061"/>
										<File Id="407173061"/>
										<File Id="758074194"/>
									</Media>
								</SwitchContainer>
								<SwitchContainer SwitchValue="{25C85962-8B03-4EBC-A1FF-74C3919ED522}">
									<Media>
										<File Id="118964264"/>
										<File Id="342450304"/>
										<File Id="545654536"/>
										<File Id="574018462"/>
										<File Id="697470634"/>
										<File Id="822535565"/>
									</Media>
								</SwitchContainer>
								<SwitchContainer SwitchValue="{7E1A2871-2BA3-48FE-A48E-BA35477EDE01}">
									<Media>
										<File Id="86339568"/>
										<File Id="132029450"/>
										<File Id="271452971"/>
										<File Id="320599554"/>
										<File Id="557396045"/>
										<File Id="830613387"/>
									</Media>
								</SwitchContainer>
								<SwitchContainer SwitchValue="{BC98C574-F032-4AFD-A97E-B01C88AFEA6D}">
									<Media>
										<File Id="118964264"/>
										<File Id="342450304"/>
										<File Id="545654536"/>
										<File Id="574018462"/>
										<File Id="697470634"/>
										<File Id="822535565"/>
									</Media>
								</SwitchContainer>
								<SwitchContainer SwitchValue="{645CE08A-1C87-4F99-9A02-CB0EBBE0C684}">
									<Media>
										<File Id="45000150"/>
										<File Id="284223424"/>
										<File Id="496634122"/>
										<File Id="614158301"/>
										<File Id="955500942"/>
										<File Id="1013155879"/>
									</Media>
								</SwitchContainer>
								<SwitchContainer SwitchValue="{9336799F-9A51-4CEE-8978-FC3583D7D618}">
									<Media>
										<File Id="118964264"/>
										<File Id="342450304"/>
										<File Id="545654536"/>
										<File Id="574018462"/>
										<File Id="697470634"/>
										<File Id="822535565"/>
									</Media>
								</SwitchContainer>
								<SwitchContainer SwitchValue="{D1DCA5AF-97CD-432B-AA6B-72F87B5BB504}">
									<Media>
										<File Id="118964264"/>
										<File Id="342450304"/>
										<File Id="545654536"/>
										<File Id="574018462"/>
										<File Id="697470634"/>
										<File Id="822535565"/>
									</Media>
								</SwitchContainer>
								<SwitchContainer SwitchValue="{3A339FDD-D978-47A9-8D47-F7C7308C3F5D}">
									<Media>
										<File Id="118964264"/>
										<File Id="342450304"/>
										<File Id="545654536"/>
										<File Id="574018462"/>
										<File Id="697470634"/>
										<File Id="822535565"/>
									</Media>
								</SwitchContainer>
								<SwitchContainer SwitchValue="{D9EB75DF-4CC0-4AD4-A8F6-1917E975CCD7}">
									<Media>
										<File Id="46106826"/>
										<File Id="134813006"/>
										<File Id="381610979"/>
										<File Id="427170479"/>
										<File Id="590730046"/>
										<File Id="593030260"/>
									</Media>
								</SwitchContainer>
							</Children>
						</SwitchContainer>
						<SwitchContainer SwitchValue="{7C08ADDB-8F7F-4FA0-8899-A06126EC92CD}">
							<DefaultSwitchValue>{B5A62B1A-4136-49D8-93E9-13FF3EF16C12}</DefaultSwitchValue>
							<Children>
								<SwitchContainer SwitchValue="{A3611407-73C1-43BB-93FA-F956D69790E9}">
									<Media>
										<File Id="83312605"/>
										<File Id="200617368"/>
										<File Id="287885192"/>
										<File Id="755095991"/>
										<File Id="931676924"/>
									</Media>
								</SwitchContainer>
								<SwitchContainer SwitchValue="{8BFF390B-ECB3-4F13-A870-8F92D48659CF}">
									<Media>
										<File Id="105517932"/>
										<File Id="128137016"/>
										<File Id="149169872"/>
										<File Id="213024346"/>
										<File Id="260592815"/>
										<File Id="391077158"/>
									</Media>
								</SwitchContainer>
								<SwitchContainer SwitchValue="{2FFB930C-2D31-4CFC-9B3F-5E2F700C60F5}">
									<Media>
										<File Id="60630466"/>
										<File Id="137964504"/>
										<File Id="526136462"/>
										<File Id="576641613"/>
										<File Id="612923756"/>
										<File Id="1062391457"/>
									</Media>
								</SwitchContainer>
								<SwitchContainer SwitchValue="{3770F718-700F-4BC9-A5CE-8F4BFDF7A781}">
									<Media>
										<File Id="105517932"/>
										<File Id="128137016"/>
										<File Id="149169872"/>
										<File Id="213024346"/>
										<File Id="260592815"/>
										<File Id="391077158"/>
									</Media>
								</SwitchContainer>
								<SwitchContainer SwitchValue="{B5A62B1A-4136-49D8-93E9-13FF3EF16C12}">
									<Media>
										<File Id="105517932"/>
										<File Id="128137016"/>
										<File Id="149169872"/>
										<File Id="213024346"/>
										<File Id="260592815"/>
										<File Id="391077158"/>
									</Media>
								</SwitchContainer>
								<SwitchContainer SwitchValue="{17E6DB35-2703-499D-B807-D0C75D81C2C1}">
									<Media>
										<File Id="105517932"/>
										<File Id="128137016"/>
										<File Id="149169872"/>
										<File Id="213024346"/>
										<File Id="260592815"/>
										<File Id="391077158"/>
									</Media>
								</SwitchContainer>
								<SwitchContainer SwitchValue="{FA3E484A-5996-4A28-BFA4-FF7EB6717409}">
									<Media>
										<File Id="105517932"/>
										<File Id="128137016"/>
										<File Id="149169872"/>
										<File Id="213024346"/>
										<File Id="260592815"/>
										<File Id="391077158"/>
									</Media>
								</SwitchContainer>
								<SwitchContainer SwitchValue="{32668058-5BF8-40EE-9E9C-2F4E2EE0A199}">
									<Media>
										<File Id="139623825"/>
										<File Id="263890707"/>
										<File Id="288736737"/>
										<File Id="317704190"/>
										<File Id="572464380"/>
										<File Id="576924454"/>
									</Media>
								</SwitchContainer>
								<SwitchContainer SwitchValue="{25C85962-8B03-4EBC-A1FF-74C3919ED522}">
									<Media>
										<File Id="105517932"/>
										<File Id="128137016"/>
										<File Id="149169872"/>
										<File Id="213024346"/>
										<File Id="260592815"/>
										<File Id="391077158"/>
									</Media>
								</SwitchContainer>
								<SwitchContainer SwitchValue="{7E1A2871-2BA3-48FE-A48E-BA35477EDE01}">
									<Media>
										<File Id="264420771"/>
										<File Id="269374664"/>
										<File Id="741324826"/>
										<File Id="762876477"/>
										<File Id="885548314"/>
										<File Id="956762804"/>
									</Media>
								</SwitchContainer>
								<SwitchContainer SwitchValue="{BC98C574-F032-4AFD-A97E-B01C88AFEA6D}">
									<Media>
										<File Id="105517932"/>
										<File Id="128137016"/>
										<File Id="149169872"/>
										<File Id="213024346"/>
										<File Id="260592815"/>
										<File Id="391077158"/>
									</Media>
								</SwitchContainer>
								<SwitchContainer SwitchValue="{645CE08A-1C87-4F99-9A02-CB0EBBE0C684}">
									<Media>
										<File Id="289083996"/>
										<File Id="388336872"/>
										<File Id="765729031"/>
										<File Id="964417384"/>
										<File Id="996996158"/>
										<File Id="1071381212"/>
									</Media>
								</SwitchContainer>
								<SwitchContainer SwitchValue="{9336799F-9A51-4CEE-8978-FC3583D7D618}">
									<Media>
										<File Id="105517932"/>
										<File Id="128137016"/>
										<File Id="149169872"/>
										<File Id="213024346"/>
										<File Id="260592815"/>
										<File Id="391077158"/>
									</Media>
								</SwitchContainer>
								<SwitchContainer SwitchValue="{D1DCA5AF-97CD-432B-AA6B-72F87B5BB504}">
									<Media>
										<File Id="105517932"/>
										<File Id="128137016"/>
										<File Id="149169872"/>
										<File Id="213024346"/>
										<File Id="260592815"/>
										<File Id="391077158"/>
									</Media>
								</SwitchContainer>
								<SwitchContainer SwitchValue="{3A339FDD-D978-47A9-8D47-F7C7308C3F5D}">
									<Media>
										<File Id="105517932"/>
										<File Id="128137016"/>
										<File Id="149169872"/>
										<File Id="213024346"/>
										<File Id="260592815"/>
										<File Id="391077158"/>
									</Media>
								</SwitchContainer>
								<SwitchContainer SwitchValue="{D9EB75DF-4CC0-4AD4-A8F6-1917E975CCD7}">
									<Media>
										<File Id="119306444"/>
										<File Id="313562469"/>
										<File Id="433106662"/>
										<File Id="654137681"/>
										<File Id="773371363"/>
										<File Id="1023464345"/>
									</Media>
								</SwitchContainer>
							</Children>
						</SwitchContainer>
					</SwitchContainers>
				</Event>
				<Event Id="215992295" Name="Player_Health" ObjectPath="\Events\Default Work Unit\Player_Health">
					<IncludedMemoryFiles>
						<File Id="234947115" Language="SFX">
							<ShortName>Heartbeat\Heartbeat_Dub.wav</ShortName>
							<Path>SFX\Heartbeat\Heartbeat_Dub_10C4C929.wem</Path>
						</File>
						<File Id="546604483" Language="SFX">
							<ShortName>Heartbeat\Heartbeat_Dub2.wav</ShortName>
							<Path>SFX\Heartbeat\Heartbeat_Dub2_10C4C929.wem</Path>
						</File>
						<File Id="1006035904" Language="SFX">
							<ShortName>Heartbeat\Heartbeat_Lub2.wav</ShortName>
							<Path>SFX\Heartbeat\Heartbeat_Lub2_10C4C929.wem</Path>
						</File>
						<File Id="1007867372" Language="SFX">
							<ShortName>Heartbeat\Heartbeat_Lub.wav</ShortName>
							<Path>SFX\Heartbeat\Heartbeat_Lub_10C4C929.wem</Path>
						</File>
					</IncludedMemoryFiles>
				</Event>
				<Event Id="3695342915" Name="Player_WeaponImpact" ObjectPath="\Events\Default Work Unit\Player_WeaponImpact">
					<IncludedMemoryFiles>
						<File Id="72287293" Language="SFX">
							<ShortName>Impacts\BAS_Impact_Sword_SurfaceType_Dirt.wav</ShortName>
							<Path>SFX\Impacts\BAS_Impact_Sword_SurfaceType_Dirt_10C4C929.wem</Path>
						</File>
						<File Id="107864555" Language="SFX">
							<ShortName>Impacts\BAS_Impact_Axe_SurfaceType_Dirt.wav</ShortName>
							<Path>SFX\Impacts\BAS_Impact_Axe_SurfaceType_Dirt_10C4C929.wem</Path>
						</File>
						<File Id="108578116" Language="SFX">
							<ShortName>Impacts\BAS_Impact_Axe_SurfaceType_Crate.wav</ShortName>
							<Path>SFX\Impacts\BAS_Impact_Axe_SurfaceType_Crate_10C4C929.wem</Path>
						</File>
						<File Id="155700374" Language="SFX">
							<ShortName>Impacts\BAS_Impact_Dagger_SurfaceType_Stone.wav</ShortName>
							<Path>SFX\Impacts\BAS_Impact_Dagger_SurfaceType_Stone_10C4C929.wem</Path>
						</File>
						<File Id="169778325" Language="SFX">
							<ShortName>Impacts\BAS_Impact_Dagger_SurfaceType_Wood.wav</ShortName>
							<Path>SFX\Impacts\BAS_Impact_Dagger_SurfaceType_Wood_10C4C929.wem</Path>
						</File>
						<File Id="227005965" Language="SFX">
							<ShortName>Impacts\BAS_Impact_PickAxe_SurfaceType_Barrel.wav</ShortName>
							<Path>SFX\Impacts\BAS_Impact_PickAxe_SurfaceType_Barrel_10C4C929.wem</Path>
						</File>
						<File Id="360611053" Language="SFX">
							<ShortName>Impacts\BAS_Impact_Dagger_SurfaceType_Dirt.wav</ShortName>
							<Path>SFX\Impacts\BAS_Impact_Dagger_SurfaceType_Dirt_10C4C929.wem</Path>
						</File>
						<File Id="365743487" Language="SFX">
							<ShortName>Impacts\BAS_Impact_PickAxe_SurfaceType_Crate.wav</ShortName>
							<Path>SFX\Impacts\BAS_Impact_PickAxe_SurfaceType_Crate_10C4C929.wem</Path>
						</File>
						<File Id="390799387" Language="SFX">
							<ShortName>Impacts\BAS_Impact_Axe_SurfaceType_Barrel.wav</ShortName>
							<Path>SFX\Impacts\BAS_Impact_Axe_SurfaceType_Barrel_10C4C929.wem</Path>
						</File>
						<File Id="457978275" Language="SFX">
							<ShortName>Impacts\BAS_Impact_Axe_SurfaceType_Leaves.wav</ShortName>
							<Path>SFX\Impacts\BAS_Impact_Axe_SurfaceType_Leaves_10C4C929.wem</Path>
						</File>
						<File Id="471650868" Language="SFX">
							<ShortName>Impacts\BAS_Impact_Sword_SurfaceType_Wood.wav</ShortName>
							<Path>SFX\Impacts\BAS_Impact_Sword_SurfaceType_Wood_10C4C929.wem</Path>
						</File>
						<File Id="631882166" Language="SFX">
							<ShortName>Impacts\BAS_Impact_Sword_SurfaceType_Leaves.wav</ShortName>
							<Path>SFX\Impacts\BAS_Impact_Sword_SurfaceType_Leaves_10C4C929.wem</Path>
						</File>
						<File Id="714063642" Language="SFX">
							<ShortName>Impacts\BAS_Impact_Axe_SurfaceType_Grass.wav</ShortName>
							<Path>SFX\Impacts\BAS_Impact_Axe_SurfaceType_Grass_10C4C929.wem</Path>
						</File>
						<File Id="777067277" Language="SFX">
							<ShortName>Impacts\BAS_Impact_Dagger_SurfaceType_Grass.wav</ShortName>
							<Path>SFX\Impacts\BAS_Impact_Dagger_SurfaceType_Grass_10C4C929.wem</Path>
						</File>
						<File Id="777171981" Language="SFX">
							<ShortName>Impacts\BAS_Impact_Dagger_SurfaceType_Leaves.wav</ShortName>
							<Path>SFX\Impacts\BAS_Impact_Dagger_SurfaceType_Leaves_10C4C929.wem</Path>
						</File>
						<File Id="783123755" Language="SFX">
							<ShortName>Impacts\BAS_Impact_Sword_SurfaceType_Barrel.wav</ShortName>
							<Path>SFX\Impacts\BAS_Impact_Sword_SurfaceType_Barrel_10C4C929.wem</Path>
						</File>
						<File Id="792821454" Language="SFX">
							<ShortName>Impacts\BAS_Impact_Axe_SurfaceType_Stone.wav</ShortName>
							<Path>SFX\Impacts\BAS_Impact_Axe_SurfaceType_Stone_10C4C929.wem</Path>
						</File>
						<File Id="849591288" Language="SFX">
							<ShortName>Impacts\BAS_Impact_Sword_SurfaceType_Crate.wav</ShortName>
							<Path>SFX\Impacts\BAS_Impact_Sword_SurfaceType_Crate_10C4C929.wem</Path>
						</File>
						<File Id="862003219" Language="SFX">
							<ShortName>Impacts\BAS_Impact_Sword_SurfaceType_Stone.wav</ShortName>
							<Path>SFX\Impacts\BAS_Impact_Sword_SurfaceType_Stone_10C4C929.wem</Path>
						</File>
						<File Id="929009122" Language="SFX">
							<ShortName>Impacts\BAS_Impact_Hammer_SurfaceType_Barrel.wav</ShortName>
							<Path>SFX\Impacts\BAS_Impact_Hammer_SurfaceType_Barrel_10C4C929.wem</Path>
						</File>
						<File Id="936007218" Language="SFX">
							<ShortName>Impacts\BAS_Impact_Hammer_SurfaceType_Crate.wav</ShortName>
							<Path>SFX\Impacts\BAS_Impact_Hammer_SurfaceType_Crate_10C4C929.wem</Path>
						</File>
						<File Id="981603683" Language="SFX">
							<ShortName>Impacts\BAS_Impact_Dagger_SurfaceType_Crate.wav</ShortName>
							<Path>SFX\Impacts\BAS_Impact_Dagger_SurfaceType_Crate_10C4C929.wem</Path>
						</File>
						<File Id="988200153" Language="SFX">
							<ShortName>Impacts\BAS_Impact_Sword_SurfaceType_Grass.wav</ShortName>
							<Path>SFX\Impacts\BAS_Impact_Sword_SurfaceType_Grass_10C4C929.wem</Path>
						</File>
						<File Id="1069727493" Language="SFX">
							<ShortName>Impacts\BAS_Impact_Dagger_SurfaceType_Barrel.wav</ShortName>
							<Path>SFX\Impacts\BAS_Impact_Dagger_SurfaceType_Barrel_10C4C929.wem</Path>
						</File>
					</IncludedMemoryFiles>
					<DefaultSwitchValue>{C5623536-76EA-44EC-B953-7F89C4255A5C}</DefaultSwitchValue>
					<SwitchContainers>
						<SwitchContainer SwitchValue="{710F0606-6756-4CC9-90B5-C755AD0E3B22}">
							<Children>
								<SwitchContainer SwitchValue="{A3611407-73C1-43BB-93FA-F956D69790E9}">
									<Media>
										<File Id="936007218"/>
									</Media>
								</SwitchContainer>
								<SwitchContainer SwitchValue="{8BFF390B-ECB3-4F13-A870-8F92D48659CF}">
									<Media>
										<File Id="936007218"/>
									</Media>
								</SwitchContainer>
								<SwitchContainer SwitchValue="{2FFB930C-2D31-4CFC-9B3F-5E2F700C60F5}">
									<Media>
										<File Id="936007218"/>
									</Media>
								</SwitchContainer>
								<SwitchContainer SwitchValue="{3770F718-700F-4BC9-A5CE-8F4BFDF7A781}">
									<Media>
										<File Id="936007218"/>
									</Media>
								</SwitchContainer>
								<SwitchContainer SwitchValue="{B5A62B1A-4136-49D8-93E9-13FF3EF16C12}">
									<Media>
										<File Id="936007218"/>
									</Media>
								</SwitchContainer>
								<SwitchContainer SwitchValue="{17E6DB35-2703-499D-B807-D0C75D81C2C1}">
									<Media>
										<File Id="929009122"/>
									</Media>
								</SwitchContainer>
								<SwitchContainer SwitchValue="{FA3E484A-5996-4A28-BFA4-FF7EB6717409}">
									<Media>
										<File Id="936007218"/>
									</Media>
								</SwitchContainer>
								<SwitchContainer SwitchValue="{32668058-5BF8-40EE-9E9C-2F4E2EE0A199}">
									<Media>
										<File Id="936007218"/>
									</Media>
								</SwitchContainer>
								<SwitchContainer SwitchValue="{25C85962-8B03-4EBC-A1FF-74C3919ED522}">
									<Media>
										<File Id="936007218"/>
									</Media>
								</SwitchContainer>
								<SwitchContainer SwitchValue="{7E1A2871-2BA3-48FE-A48E-BA35477EDE01}">
									<Media>
										<File Id="936007218"/>
									</Media>
								</SwitchContainer>
								<SwitchContainer SwitchValue="{BC98C574-F032-4AFD-A97E-B01C88AFEA6D}">
									<Media>
										<File Id="936007218"/>
									</Media>
								</SwitchContainer>
								<SwitchContainer SwitchValue="{645CE08A-1C87-4F99-9A02-CB0EBBE0C684}">
									<Media>
										<File Id="936007218"/>
									</Media>
								</SwitchContainer>
								<SwitchContainer SwitchValue="{9336799F-9A51-4CEE-8978-FC3583D7D618}">
									<Media>
										<File Id="936007218"/>
									</Media>
								</SwitchContainer>
								<SwitchContainer SwitchValue="{D1DCA5AF-97CD-432B-AA6B-72F87B5BB504}">
									<Media>
										<File Id="936007218"/>
									</Media>
								</SwitchContainer>
								<SwitchContainer SwitchValue="{3A339FDD-D978-47A9-8D47-F7C7308C3F5D}">
									<Media>
										<File Id="936007218"/>
									</Media>
								</SwitchContainer>
								<SwitchContainer SwitchValue="{D9EB75DF-4CC0-4AD4-A8F6-1917E975CCD7}">
									<Media>
										<File Id="936007218"/>
									</Media>
								</SwitchContainer>
							</Children>
						</SwitchContainer>
						<SwitchContainer SwitchValue="{C5623536-76EA-44EC-B953-7F89C4255A5C}">
							<DefaultSwitchValue>{B5A62B1A-4136-49D8-93E9-13FF3EF16C12}</DefaultSwitchValue>
							<Children>
								<SwitchContainer SwitchValue="{A3611407-73C1-43BB-93FA-F956D69790E9}">
									<Media>
										<File Id="72287293"/>
									</Media>
								</SwitchContainer>
								<SwitchContainer SwitchValue="{8BFF390B-ECB3-4F13-A870-8F92D48659CF}">
									<Media>
										<File Id="631882166"/>
									</Media>
								</SwitchContainer>
								<SwitchContainer SwitchValue="{2FFB930C-2D31-4CFC-9B3F-5E2F700C60F5}">
									<Media>
										<File Id="72287293"/>
									</Media>
								</SwitchContainer>
								<SwitchContainer SwitchValue="{B5A62B1A-4136-49D8-93E9-13FF3EF16C12}">
									<Media>
										<File Id="72287293"/>
									</Media>
								</SwitchContainer>
								<SwitchContainer SwitchValue="{17E6DB35-2703-499D-B807-D0C75D81C2C1}">
									<Media>
										<File Id="783123755"/>
									</Media>
								</SwitchContainer>
								<SwitchContainer SwitchValue="{FA3E484A-5996-4A28-BFA4-FF7EB6717409}">
									<Media>
										<File Id="72287293"/>
									</Media>
								</SwitchContainer>
								<SwitchContainer SwitchValue="{32668058-5BF8-40EE-9E9C-2F4E2EE0A199}">
									<Media>
										<File Id="988200153"/>
									</Media>
								</SwitchContainer>
								<SwitchContainer SwitchValue="{25C85962-8B03-4EBC-A1FF-74C3919ED522}">
									<Media>
										<File Id="72287293"/>
									</Media>
								</SwitchContainer>
								<SwitchContainer SwitchValue="{7E1A2871-2BA3-48FE-A48E-BA35477EDE01}">
									<Media>
										<File Id="72287293"/>
									</Media>
								</SwitchContainer>
								<SwitchContainer SwitchValue="{645CE08A-1C87-4F99-9A02-CB0EBBE0C684}">
									<Media>
										<File Id="862003219"/>
									</Media>
								</SwitchContainer>
								<SwitchContainer SwitchValue="{D1DCA5AF-97CD-432B-AA6B-72F87B5BB504}">
									<Media>
										<File Id="72287293"/>
									</Media>
								</SwitchContainer>
								<SwitchContainer SwitchValue="{3A339FDD-D978-47A9-8D47-F7C7308C3F5D}">
									<Media>
										<File Id="849591288"/>
									</Media>
								</SwitchContainer>
								<SwitchContainer SwitchValue="{D9EB75DF-4CC0-4AD4-A8F6-1917E975CCD7}">
									<Media>
										<File Id="471650868"/>
									</Media>
								</SwitchContainer>
							</Children>
						</SwitchContainer>
						<SwitchContainer SwitchValue="{7E13F795-E59C-4FA1-BADB-FB07B6F1A2C3}">
							<DefaultSwitchValue>{3A339FDD-D978-47A9-8D47-F7C7308C3F5D}</DefaultSwitchValue>
							<Children>
								<SwitchContainer SwitchValue="{A3611407-73C1-43BB-93FA-F956D69790E9}">
									<Media>
										<File Id="365743487"/>
									</Media>
								</SwitchContainer>
								<SwitchContainer SwitchValue="{8BFF390B-ECB3-4F13-A870-8F92D48659CF}">
									<Media>
										<File Id="365743487"/>
									</Media>
								</SwitchContainer>
								<SwitchContainer SwitchValue="{2FFB930C-2D31-4CFC-9B3F-5E2F700C60F5}">
									<Media>
										<File Id="365743487"/>
									</Media>
								</SwitchContainer>
								<SwitchContainer SwitchValue="{3770F718-700F-4BC9-A5CE-8F4BFDF7A781}">
									<Media>
										<File Id="365743487"/>
									</Media>
								</SwitchContainer>
								<SwitchContainer SwitchValue="{B5A62B1A-4136-49D8-93E9-13FF3EF16C12}">
									<Media>
										<File Id="365743487"/>
									</Media>
								</SwitchContainer>
								<SwitchContainer SwitchValue="{17E6DB35-2703-499D-B807-D0C75D81C2C1}">
									<Media>
										<File Id="227005965"/>
									</Media>
								</SwitchContainer>
								<SwitchContainer SwitchValue="{FA3E484A-5996-4A28-BFA4-FF7EB6717409}">
									<Media>
										<File Id="365743487"/>
									</Media>
								</SwitchContainer>
								<SwitchContainer SwitchValue="{32668058-5BF8-40EE-9E9C-2F4E2EE0A199}">
									<Media>
										<File Id="365743487"/>
									</Media>
								</SwitchContainer>
								<SwitchContainer SwitchValue="{25C85962-8B03-4EBC-A1FF-74C3919ED522}">
									<Media>
										<File Id="365743487"/>
									</Media>
								</SwitchContainer>
								<SwitchContainer SwitchValue="{7E1A2871-2BA3-48FE-A48E-BA35477EDE01}">
									<Media>
										<File Id="365743487"/>
									</Media>
								</SwitchContainer>
								<SwitchContainer SwitchValue="{BC98C574-F032-4AFD-A97E-B01C88AFEA6D}">
									<Media>
										<File Id="365743487"/>
									</Media>
								</SwitchContainer>
								<SwitchContainer SwitchValue="{645CE08A-1C87-4F99-9A02-CB0EBBE0C684}">
									<Media>
										<File Id="365743487"/>
									</Media>
								</SwitchContainer>
								<SwitchContainer SwitchValue="{9336799F-9A51-4CEE-8978-FC3583D7D618}">
									<Media>
										<File Id="365743487"/>
									</Media>
								</SwitchContainer>
								<SwitchContainer SwitchValue="{D1DCA5AF-97CD-432B-AA6B-72F87B5BB504}">
									<Media>
										<File Id="365743487"/>
									</Media>
								</SwitchContainer>
								<SwitchContainer SwitchValue="{3A339FDD-D978-47A9-8D47-F7C7308C3F5D}">
									<Media>
										<File Id="365743487"/>
									</Media>
								</SwitchContainer>
								<SwitchContainer SwitchValue="{D9EB75DF-4CC0-4AD4-A8F6-1917E975CCD7}">
									<Media>
										<File Id="365743487"/>
									</Media>
								</SwitchContainer>
							</Children>
						</SwitchContainer>
						<SwitchContainer SwitchValue="{6F76D9B2-ED84-41FA-B43E-F26FCF90D7EC}">
							<DefaultSwitchValue>{B5A62B1A-4136-49D8-93E9-13FF3EF16C12}</DefaultSwitchValue>
							<Children>
								<SwitchContainer SwitchValue="{A3611407-73C1-43BB-93FA-F956D69790E9}">
									<Media>
										<File Id="360611053"/>
									</Media>
								</SwitchContainer>
								<SwitchContainer SwitchValue="{8BFF390B-ECB3-4F13-A870-8F92D48659CF}">
									<Media>
										<File Id="777171981"/>
									</Media>
								</SwitchContainer>
								<SwitchContainer SwitchValue="{2FFB930C-2D31-4CFC-9B3F-5E2F700C60F5}">
									<Media>
										<File Id="360611053"/>
									</Media>
								</SwitchContainer>
								<SwitchContainer SwitchValue="{3770F718-700F-4BC9-A5CE-8F4BFDF7A781}">
									<Media>
										<File Id="360611053"/>
									</Media>
								</SwitchContainer>
								<SwitchContainer SwitchValue="{B5A62B1A-4136-49D8-93E9-13FF3EF16C12}">
									<Media>
										<File Id="360611053"/>
									</Media>
								</SwitchContainer>
								<SwitchContainer SwitchValue="{17E6DB35-2703-499D-B807-D0C75D81C2C1}">
									<Media>
										<File Id="1069727493"/>
									</Media>
								</SwitchContainer>
								<SwitchContainer SwitchValue="{FA3E484A-5996-4A28-BFA4-FF7EB6717409}">
									<Media>
										<File Id="360611053"/>
									</Media>
								</SwitchContainer>
								<SwitchContainer SwitchValue="{32668058-5BF8-40EE-9E9C-2F4E2EE0A199}">
									<Media>
										<File Id="777067277"/>
									</Media>
								</SwitchContainer>
								<SwitchContainer SwitchValue="{25C85962-8B03-4EBC-A1FF-74C3919ED522}">
									<Media>
										<File Id="360611053"/>
									</Media>
								</SwitchContainer>
								<SwitchContainer SwitchValue="{7E1A2871-2BA3-48FE-A48E-BA35477EDE01}">
									<Media>
										<File Id="360611053"/>
									</Media>
								</SwitchContainer>
								<SwitchContainer SwitchValue="{BC98C574-F032-4AFD-A97E-B01C88AFEA6D}">
									<Media>
										<File Id="360611053"/>
									</Media>
								</SwitchContainer>
								<SwitchContainer SwitchValue="{645CE08A-1C87-4F99-9A02-CB0EBBE0C684}">
									<Media>
										<File Id="155700374"/>
									</Media>
								</SwitchContainer>
								<SwitchContainer SwitchValue="{9336799F-9A51-4CEE-8978-FC3583D7D618}">
									<Media>
										<File Id="360611053"/>
									</Media>
								</SwitchContainer>
								<SwitchContainer SwitchValue="{D1DCA5AF-97CD-432B-AA6B-72F87B5BB504}">
									<Media>
										<File Id="360611053"/>
									</Media>
								</SwitchContainer>
								<SwitchContainer SwitchValue="{3A339FDD-D978-47A9-8D47-F7C7308C3F5D}">
									<Media>
										<File Id="981603683"/>
									</Media>
								</SwitchContainer>
								<SwitchContainer SwitchValue="{D9EB75DF-4CC0-4AD4-A8F6-1917E975CCD7}">
									<Media>
										<File Id="169778325"/>
									</Media>
								</SwitchContainer>
							</Children>
						</SwitchContainer>
						<SwitchContainer SwitchValue="{0025D0F3-232A-4230-9CF5-FAA707BEECB4}">
							<Children>
								<SwitchContainer SwitchValue="{A3611407-73C1-43BB-93FA-F956D69790E9}">
									<Media>
										<File Id="107864555"/>
									</Media>
								</SwitchContainer>
								<SwitchContainer SwitchValue="{8BFF390B-ECB3-4F13-A870-8F92D48659CF}">
									<Media>
										<File Id="457978275"/>
									</Media>
								</SwitchContainer>
								<SwitchContainer SwitchValue="{2FFB930C-2D31-4CFC-9B3F-5E2F700C60F5}">
									<Media>
										<File Id="107864555"/>
									</Media>
								</SwitchContainer>
								<SwitchContainer SwitchValue="{3770F718-700F-4BC9-A5CE-8F4BFDF7A781}">
									<Media>
										<File Id="107864555"/>
									</Media>
								</SwitchContainer>
								<SwitchContainer SwitchValue="{B5A62B1A-4136-49D8-93E9-13FF3EF16C12}">
									<Media>
										<File Id="107864555"/>
									</Media>
								</SwitchContainer>
								<SwitchContainer SwitchValue="{17E6DB35-2703-499D-B807-D0C75D81C2C1}">
									<Media>
										<File Id="390799387"/>
									</Media>
								</SwitchContainer>
								<SwitchContainer SwitchValue="{FA3E484A-5996-4A28-BFA4-FF7EB6717409}">
									<Media>
										<File Id="107864555"/>
									</Media>
								</SwitchContainer>
								<SwitchContainer SwitchValue="{32668058-5BF8-40EE-9E9C-2F4E2EE0A199}">
									<Media>
										<File Id="714063642"/>
									</Media>
								</SwitchContainer>
								<SwitchContainer SwitchValue="{25C85962-8B03-4EBC-A1FF-74C3919ED522}">
									<Media>
										<File Id="107864555"/>
									</Media>
								</SwitchContainer>
								<SwitchContainer SwitchValue="{7E1A2871-2BA3-48FE-A48E-BA35477EDE01}">
									<Media>
										<File Id="107864555"/>
									</Media>
								</SwitchContainer>
								<SwitchContainer SwitchValue="{BC98C574-F032-4AFD-A97E-B01C88AFEA6D}">
									<Media>
										<File Id="107864555"/>
									</Media>
								</SwitchContainer>
								<SwitchContainer SwitchValue="{645CE08A-1C87-4F99-9A02-CB0EBBE0C684}">
									<Media>
										<File Id="792821454"/>
									</Media>
								</SwitchContainer>
								<SwitchContainer SwitchValue="{9336799F-9A51-4CEE-8978-FC3583D7D618}">
									<Media>
										<File Id="107864555"/>
									</Media>
								</SwitchContainer>
								<SwitchContainer SwitchValue="{D1DCA5AF-97CD-432B-AA6B-72F87B5BB504}">
									<Media>
										<File Id="107864555"/>
									</Media>
								</SwitchContainer>
								<SwitchContainer SwitchValue="{3A339FDD-D978-47A9-8D47-F7C7308C3F5D}">
									<Media>
										<File Id="108578116"/>
									</Media>
								</SwitchContainer>
								<SwitchContainer SwitchValue="{D9EB75DF-4CC0-4AD4-A8F6-1917E975CCD7}">
									<Media>
										<File Id="107864555"/>
									</Media>
								</SwitchContainer>
							</Children>
						</SwitchContainer>
					</SwitchContainers>
				</Event>
				<Event Id="3240473869" Name="Quest_Complete" ObjectPath="\Events\Default Work Unit\Quest_Complete"/>
				<Event Id="844130829" Name="Quest_CompleteCollection" ObjectPath="\Events\Default Work Unit\Quest_CompleteCollection"/>
				<Event Id="452547817" Name="Stop_All" ObjectPath="\Events\Default Work Unit\Stop_All"/>
				<Event Id="156563189" Name="UI_Button_Down" ObjectPath="\Events\Default Work Unit\UI_Button_Down">
					<IncludedMemoryFiles>
						<File Id="269251227" Language="SFX">
							<ShortName>UI\BAS_Button_Over.wav</ShortName>
							<Path>SFX\UI\BAS_Button_Over_10C4C929.wem</Path>
						</File>
					</IncludedMemoryFiles>
				</Event>
				<Event Id="18309885" Name="UI_Button_Enter" ObjectPath="\Events\Default Work Unit\UI_Button_Enter">
					<IncludedMemoryFiles>
						<File Id="163811544" Language="SFX">
							<ShortName>UI\BAS_Button_Enter.wav</ShortName>
							<Path>SFX\UI\BAS_Button_Enter_10C4C929.wem</Path>
						</File>
					</IncludedMemoryFiles>
				</Event>
				<Event Id="2325560497" Name="UI_Button_Exit" ObjectPath="\Events\Default Work Unit\UI_Button_Exit">
					<IncludedMemoryFiles>
						<File Id="163811544" Language="SFX">
							<ShortName>UI\BAS_Button_Enter.wav</ShortName>
							<Path>SFX\UI\BAS_Button_Enter_10C4C929.wem</Path>
						</File>
					</IncludedMemoryFiles>
				</Event>
				<Event Id="15662850" Name="UI_Button_Up" ObjectPath="\Events\Default Work Unit\UI_Button_Up">
					<IncludedMemoryFiles>
						<File Id="269251227" Language="SFX">
							<ShortName>UI\BAS_Button_Over.wav</ShortName>
							<Path>SFX\UI\BAS_Button_Over_10C4C929.wem</Path>
						</File>
					</IncludedMemoryFiles>
				</Event>
				<Event Id="2278290679" Name="UI_Inventory_Close" ObjectPath="\Events\Default Work Unit\UI_Inventory_Close">
					<IncludedMemoryFiles>
						<File Id="254421272" Language="SFX">
							<ShortName>UI\BAS_Inventory_Close.wav</ShortName>
							<Path>SFX\UI\BAS_Inventory_Close_10C4C929.wem</Path>
						</File>
					</IncludedMemoryFiles>
				</Event>
				<Event Id="2199611969" Name="UI_Inventory_Open" ObjectPath="\Events\Default Work Unit\UI_Inventory_Open">
					<IncludedMemoryFiles>
						<File Id="288094772" Language="SFX">
							<ShortName>UI\BAS_Inventory_Open.wav</ShortName>
							<Path>SFX\UI\BAS_Inventory_Open_10C4C929.wem</Path>
						</File>
					</IncludedMemoryFiles>
				</Event>
				<Event Id="3749307760" Name="UI_Inventory_Roll" ObjectPath="\Events\Default Work Unit\UI_Inventory_Roll">
					<IncludedMemoryFiles>
						<File Id="320657803" Language="SFX">
							<ShortName>UI\BAS_Inventory_Scroll.wav</ShortName>
							<Path>SFX\UI\BAS_Inventory_Scroll_10C4C929.wem</Path>
						</File>
					</IncludedMemoryFiles>
				</Event>
				<Event Id="3237189652" Name="UI_Menu_Pause" ObjectPath="\Events\Default Work Unit\UI_Menu_Pause">
					<IncludedMemoryFiles>
						<File Id="971609785" Language="SFX">
							<ShortName>UI\BAS_Button_Open.wav</ShortName>
							<Path>SFX\UI\BAS_Button_Open_10C4C929.wem</Path>
						</File>
					</IncludedMemoryFiles>
				</Event>
				<Event Id="1464993479" Name="UI_Menu_Resume" ObjectPath="\Events\Default Work Unit\UI_Menu_Resume">
					<IncludedMemoryFiles>
						<File Id="607768939" Language="SFX">
							<ShortName>UI\BAS_Button_Close.wav</ShortName>
							<Path>SFX\UI\BAS_Button_Close_10C4C929.wem</Path>
						</File>
					</IncludedMemoryFiles>
				</Event>
				<Event Id="3474566310" Name="UI_Menu_Select" ObjectPath="\Events\Default Work Unit\UI_Menu_Select">
					<IncludedMemoryFiles>
						<File Id="708289879" Language="SFX">
							<ShortName>UI\BAS_Inventory_Select.wav</ShortName>
							<Path>SFX\UI\BAS_Inventory_Select_10C4C929.wem</Path>
						</File>
					</IncludedMemoryFiles>
				</Event>
				<Event Id="750089663" Name="UI_Menu_Teleport" ObjectPath="\Events\Default Work Unit\UI_Menu_Teleport">
					<IncludedMemoryFiles>
						<File Id="900050537" Language="SFX">
							<ShortName>UI\BAS_Button_Teleport.wav</ShortName>
							<Path>SFX\UI\BAS_Button_Teleport_10C4C929.wem</Path>
						</File>
					</IncludedMemoryFiles>
				</Event>
				<Event Id="3567233235" Name="UI_Quest_Roll_Close" ObjectPath="\Events\Default Work Unit\UI_Quest_Roll_Close">
					<IncludedMemoryFiles>
						<File Id="161770584" Language="SFX">
							<ShortName>UI\BAS_QuestRoll_Close.wav</ShortName>
							<Path>SFX\UI\BAS_QuestRoll_Close_10C4C929.wem</Path>
						</File>
					</IncludedMemoryFiles>
				</Event>
				<Event Id="1399152593" Name="UI_Quest_Roll_Hide" ObjectPath="\Events\Default Work Unit\UI_Quest_Roll_Hide">
					<IncludedMemoryFiles>
						<File Id="288094772" Language="SFX">
							<ShortName>UI\BAS_Inventory_Open.wav</ShortName>
							<Path>SFX\UI\BAS_Inventory_Open_10C4C929.wem</Path>
						</File>
					</IncludedMemoryFiles>
				</Event>
				<Event Id="2702327653" Name="UI_Quest_Roll_Open" ObjectPath="\Events\Default Work Unit\UI_Quest_Roll_Open">
					<IncludedMemoryFiles>
						<File Id="401018015" Language="SFX">
							<ShortName>UI\BAS_QuestRoll_Open.wav</ShortName>
							<Path>SFX\UI\BAS_QuestRoll_Open_10C4C929.wem</Path>
						</File>
					</IncludedMemoryFiles>
				</Event>
				<Event Id="3524454690" Name="UI_Quest_Roll_Show" ObjectPath="\Events\Default Work Unit\UI_Quest_Roll_Show">
					<IncludedMemoryFiles>
						<File Id="288094772" Language="SFX">
							<ShortName>UI\BAS_Inventory_Open.wav</ShortName>
							<Path>SFX\UI\BAS_Inventory_Open_10C4C929.wem</Path>
						</File>
					</IncludedMemoryFiles>
				</Event>
			</IncludedEvents>
			<GameParameters>
				<GameParameter Id="207908541" Name="Time_of_Day" ObjectPath="\Game Parameters\Default Work Unit\Time_of_Day"/>
				<GameParameter Id="215992295" Name="Player_Health" ObjectPath="\Game Parameters\Default Work Unit\Player_Health"/>
				<GameParameter Id="2471758783" Name="Player_MovementSpeed" ObjectPath="\Game Parameters\Default Work Unit\Player_MovementSpeed"/>
				<GameParameter Id="3251833556" Name="Player_Weapon_Type" ObjectPath="\Game Parameters\Default Work Unit\Player_Weapon_Type"/>
				<GameParameter Id="4064446173" Name="Surface_Type" ObjectPath="\Game Parameters\Default Work Unit\Surface_Type"/>
			</GameParameters>
			<StateGroups>
				<StateGroup Id="2106907484" Name="Music_Regions" ObjectPath="\States\Default Work Unit\Music_Regions" GUID="{C851B23C-75F7-45D8-8A3B-9258A02A11EA}">
					<States>
						<State Id="748895195" Name="None" ObjectPath="\States\Default Work Unit\Music_Regions\None" GUID="{3E08916B-358F-4B95-9949-810EB3575930}"/>
						<State Id="4122393694" Name="Cave" ObjectPath="\States\Default Work Unit\Music_Regions\Cave" GUID="{399C57E6-3EB3-4342-A2D9-58F9298F6B08}"/>
						<State Id="3945572659" Name="Village" ObjectPath="\States\Default Work Unit\Music_Regions\Village" GUID="{0C2F6D1C-FA40-42FB-9F9A-7CDAB9AC23E7}"/>
						<State Id="1850388778" Name="Desert" ObjectPath="\States\Default Work Unit\Music_Regions\Desert" GUID="{AA980662-8B5B-4247-B0CD-4C1BEB1B50DD}"/>
						<State Id="608898761" Name="Dungeon" ObjectPath="\States\Default Work Unit\Music_Regions\Dungeon" GUID="{1083B2A5-4AAD-4FC3-B245-6EC2E345567F}"/>
						<State Id="3160623154" Name="Silent" ObjectPath="\States\Default Work Unit\Music_Regions\Silent" GUID="{4124A71E-9192-4796-A94E-4195D16349C3}"/>
						<State Id="3424056949" Name="Nowhere" ObjectPath="\States\Default Work Unit\Music_Regions\Nowhere" GUID="{61BDAE3A-0243-4F48-A840-D64D9589B424}"/>
						<State Id="1421251628" Name="Woodlands" ObjectPath="\States\Default Work Unit\Music_Regions\Woodlands" GUID="{67D03A08-4A6F-4CDE-8E3E-E2364F7F33B0}"/>
						<State Id="3132368115" Name="WwizardHouse" ObjectPath="\States\Default Work Unit\Music_Regions\WwizardHouse" GUID="{AD69625B-0DF9-4CD1-8912-47D4AFA2C60D}"/>
					</States>
				</StateGroup>
			</StateGroups>
			<SwitchGroups>
				<SwitchGroup Id="207908541" Name="Time_of_Day" ObjectPath="\Switches\Default Work Unit\Time_of_Day" GUID="{0DB4C265-2556-4FF2-88C0-8853D0EEABBB}">
					<Switches>
						<Switch Id="311764537" Name="Day" ObjectPath="\Switches\Default Work Unit\Time_of_Day\Day" GUID="{12B8D30A-EE92-4CBB-A492-4914DF46DB52}"/>
						<Switch Id="1011622525" Name="Night" ObjectPath="\Switches\Default Work Unit\Time_of_Day\Night" GUID="{23EEB13D-026D-43C2-A3DA-96B33F5888AE}"/>
					</Switches>
				</SwitchGroup>
				<SwitchGroup Id="1467963052" Name="Weapons" ObjectPath="\Switches\Default Work Unit\Weapons" GUID="{B3A5A21B-D96D-469E-9EA2-D2EBC3B63D8C}">
					<Switches>
						<Switch Id="2454616260" Name="Sword" ObjectPath="\Switches\Default Work Unit\Weapons\Sword" GUID="{C5623536-76EA-44EC-B953-7F89C4255A5C}"/>
						<Switch Id="765201635" Name="Axe" ObjectPath="\Switches\Default Work Unit\Weapons\Axe" GUID="{0025D0F3-232A-4230-9CF5-FAA707BEECB4}"/>
						<Switch Id="3732162827" Name="Dagger" ObjectPath="\Switches\Default Work Unit\Weapons\Dagger" GUID="{6F76D9B2-ED84-41FA-B43E-F26FCF90D7EC}"/>
						<Switch Id="490825222" Name="PickAxe" ObjectPath="\Switches\Default Work Unit\Weapons\PickAxe" GUID="{7E13F795-E59C-4FA1-BADB-FB07B6F1A2C3}"/>
						<Switch Id="703486095" Name="Hammer" ObjectPath="\Switches\Default Work Unit\Weapons\Hammer" GUID="{710F0606-6756-4CC9-90B5-C755AD0E3B22}"/>
					</Switches>
				</SwitchGroup>
				<SwitchGroup Id="2385628198" Name="Footsteps" ObjectPath="\Switches\Default Work Unit\Footsteps" GUID="{9C491688-854F-44B0-AAA4-BC2C31B39366}">
					<Switches>
						<Switch Id="712161704" Name="Run" ObjectPath="\Switches\Default Work Unit\Footsteps\Run" GUID="{495D2402-2BA5-491C-AB8F-A1A2D1E192F5}"/>
						<Switch Id="2108779966" Name="Walk" ObjectPath="\Switches\Default Work Unit\Footsteps\Walk" GUID="{7C08ADDB-8F7F-4FA0-8899-A06126EC92CD}"/>
					</Switches>
				</SwitchGroup>
				<SwitchGroup Id="4064446173" Name="Surface_Type" ObjectPath="\Switches\Default Work Unit\Surface_Type" GUID="{BC48BBE3-426A-43BF-8A46-68A45295A6F3}">
					<Switches>
						<Switch Id="2195636714" Name="Dirt" ObjectPath="\Switches\Default Work Unit\Surface_Type\Dirt" GUID="{B5A62B1A-4136-49D8-93E9-13FF3EF16C12}"/>
						<Switch Id="4248645337" Name="Grass" ObjectPath="\Switches\Default Work Unit\Surface_Type\Grass" GUID="{32668058-5BF8-40EE-9E9C-2F4E2EE0A199}"/>
						<Switch Id="286660663" Name="Rubble" ObjectPath="\Switches\Default Work Unit\Surface_Type\Rubble" GUID="{A3611407-73C1-43BB-93FA-F956D69790E9}"/>
						<Switch Id="803837735" Name="Sand" ObjectPath="\Switches\Default Work Unit\Surface_Type\Sand" GUID="{7E1A2871-2BA3-48FE-A48E-BA35477EDE01}"/>
						<Switch Id="1216965916" Name="Stone" ObjectPath="\Switches\Default Work Unit\Surface_Type\Stone" GUID="{645CE08A-1C87-4F99-9A02-CB0EBBE0C684}"/>
						<Switch Id="2654748154" Name="Water" ObjectPath="\Switches\Default Work Unit\Surface_Type\Water" GUID="{2FFB930C-2D31-4CFC-9B3F-5E2F700C60F5}"/>
						<Switch Id="2058049674" Name="Wood" ObjectPath="\Switches\Default Work Unit\Surface_Type\Wood" GUID="{D9EB75DF-4CC0-4AD4-A8F6-1917E975CCD7}"/>
						<Switch Id="389757836" Name="Agent" ObjectPath="\Switches\Default Work Unit\Surface_Type\Agent" GUID="{FA3E484A-5996-4A28-BFA4-FF7EB6717409}"/>
						<Switch Id="442447909" Name="Barrel" ObjectPath="\Switches\Default Work Unit\Surface_Type\Barrel" GUID="{17E6DB35-2703-499D-B807-D0C75D81C2C1}"/>
						<Switch Id="3098439042" Name="Crate" ObjectPath="\Switches\Default Work Unit\Surface_Type\Crate" GUID="{3A339FDD-D978-47A9-8D47-F7C7308C3F5D}"/>
						<Switch Id="3444057113" Name="Crystal" ObjectPath="\Switches\Default Work Unit\Surface_Type\Crystal" GUID="{25C85962-8B03-4EBC-A1FF-74C3919ED522}"/>
						<Switch Id="582824249" Name="Leaves" ObjectPath="\Switches\Default Work Unit\Surface_Type\Leaves" GUID="{8BFF390B-ECB3-4F13-A870-8F92D48659CF}"/>
						<Switch Id="2473969246" Name="Metal" ObjectPath="\Switches\Default Work Unit\Surface_Type\Metal" GUID="{D1DCA5AF-97CD-432B-AA6B-72F87B5BB504}"/>
						<Switch Id="1647104456" Name="Enemy_EvilCrawler" ObjectPath="\Switches\Default Work Unit\Surface_Type\Enemy_EvilCrawler" GUID="{BC98C574-F032-4AFD-A97E-B01C88AFEA6D}"/>
						<Switch Id="3065846598" Name="Enemy_EvilHead" ObjectPath="\Switches\Default Work Unit\Surface_Type\Enemy_EvilHead" GUID="{9336799F-9A51-4CEE-8978-FC3583D7D618}"/>
						<Switch Id="3276966729" Name="Enemy_EvilSpitPlant" ObjectPath="\Switches\Default Work Unit\Surface_Type\Enemy_EvilSpitPlant" GUID="{3770F718-700F-4BC9-A5CE-8F4BFDF7A781}"/>
					</Switches>
				</SwitchGroup>
			</SwitchGroups>
		</SoundBank>
		<SoundBank Id="152105657" Language="SFX" Hash="1995650717">
			<ObjectPath>\SoundBanks\Default Work Unit\TitleScreen</ObjectPath>
			<ShortName>TitleScreen</ShortName>
			<Path>TitleScreen.bnk</Path>
			<IncludedEvents>
				<Event Id="1049266392" Name="Ambient_Region_Woodlands" ObjectPath="\Events\Default Work Unit\Ambient_Region_Woodlands">
					<IncludedMemoryFiles>
						<File Id="1069939439" Language="SFX">
							<ShortName>Ambient_Background\BAS_amb_forest_day_background_loop_01.wav</ShortName>
							<Path>SFX\Ambient_Background\BAS_amb_forest_day_background_loop_01_9CDB22D5.wem</Path>
						</File>
					</IncludedMemoryFiles>
				</Event>
				<Event Id="1532327793" Name="Music_TitleScreen" ObjectPath="\Events\Default Work Unit\Music_TitleScreen">
					<IncludedMemoryFiles>
						<File Id="66374312" Language="SFX">
							<ShortName>Music\TitleScreen_120BPM_4_4_L41M_P2M.wav</ShortName>
							<Path>SFX\Music\TitleScreen_120BPM_4_4_L41M_P2M_D79FB2B7.wem</Path>
						</File>
					</IncludedMemoryFiles>
				</Event>
				<Event Id="156563189" Name="UI_Button_Down" ObjectPath="\Events\Default Work Unit\UI_Button_Down">
					<IncludedMemoryFiles>
						<File Id="269251227" Language="SFX">
							<ShortName>UI\BAS_Button_Over.wav</ShortName>
							<Path>SFX\UI\BAS_Button_Over_10C4C929.wem</Path>
						</File>
					</IncludedMemoryFiles>
				</Event>
				<Event Id="18309885" Name="UI_Button_Enter" ObjectPath="\Events\Default Work Unit\UI_Button_Enter">
					<IncludedMemoryFiles>
						<File Id="163811544" Language="SFX">
							<ShortName>UI\BAS_Button_Enter.wav</ShortName>
							<Path>SFX\UI\BAS_Button_Enter_10C4C929.wem</Path>
						</File>
					</IncludedMemoryFiles>
				</Event>
				<Event Id="2325560497" Name="UI_Button_Exit" ObjectPath="\Events\Default Work Unit\UI_Button_Exit">
					<IncludedMemoryFiles>
						<File Id="163811544" Language="SFX">
							<ShortName>UI\BAS_Button_Enter.wav</ShortName>
							<Path>SFX\UI\BAS_Button_Enter_10C4C929.wem</Path>
						</File>
					</IncludedMemoryFiles>
				</Event>
				<Event Id="15662850" Name="UI_Button_Up" ObjectPath="\Events\Default Work Unit\UI_Button_Up">
					<IncludedMemoryFiles>
						<File Id="269251227" Language="SFX">
							<ShortName>UI\BAS_Button_Over.wav</ShortName>
							<Path>SFX\UI\BAS_Button_Over_10C4C929.wem</Path>
						</File>
					</IncludedMemoryFiles>
				</Event>
				<Event Id="2278290679" Name="UI_Inventory_Close" ObjectPath="\Events\Default Work Unit\UI_Inventory_Close">
					<IncludedMemoryFiles>
						<File Id="254421272" Language="SFX">
							<ShortName>UI\BAS_Inventory_Close.wav</ShortName>
							<Path>SFX\UI\BAS_Inventory_Close_10C4C929.wem</Path>
						</File>
					</IncludedMemoryFiles>
				</Event>
				<Event Id="2199611969" Name="UI_Inventory_Open" ObjectPath="\Events\Default Work Unit\UI_Inventory_Open">
					<IncludedMemoryFiles>
						<File Id="288094772" Language="SFX">
							<ShortName>UI\BAS_Inventory_Open.wav</ShortName>
							<Path>SFX\UI\BAS_Inventory_Open_10C4C929.wem</Path>
						</File>
					</IncludedMemoryFiles>
				</Event>
				<Event Id="3749307760" Name="UI_Inventory_Roll" ObjectPath="\Events\Default Work Unit\UI_Inventory_Roll">
					<IncludedMemoryFiles>
						<File Id="320657803" Language="SFX">
							<ShortName>UI\BAS_Inventory_Scroll.wav</ShortName>
							<Path>SFX\UI\BAS_Inventory_Scroll_10C4C929.wem</Path>
						</File>
					</IncludedMemoryFiles>
				</Event>
				<Event Id="3237189652" Name="UI_Menu_Pause" ObjectPath="\Events\Default Work Unit\UI_Menu_Pause">
					<IncludedMemoryFiles>
						<File Id="971609785" Language="SFX">
							<ShortName>UI\BAS_Button_Open.wav</ShortName>
							<Path>SFX\UI\BAS_Button_Open_10C4C929.wem</Path>
						</File>
					</IncludedMemoryFiles>
				</Event>
				<Event Id="1464993479" Name="UI_Menu_Resume" ObjectPath="\Events\Default Work Unit\UI_Menu_Resume">
					<IncludedMemoryFiles>
						<File Id="607768939" Language="SFX">
							<ShortName>UI\BAS_Button_Close.wav</ShortName>
							<Path>SFX\UI\BAS_Button_Close_10C4C929.wem</Path>
						</File>
					</IncludedMemoryFiles>
				</Event>
				<Event Id="3474566310" Name="UI_Menu_Select" ObjectPath="\Events\Default Work Unit\UI_Menu_Select">
					<IncludedMemoryFiles>
						<File Id="708289879" Language="SFX">
							<ShortName>UI\BAS_Inventory_Select.wav</ShortName>
							<Path>SFX\UI\BAS_Inventory_Select_10C4C929.wem</Path>
						</File>
					</IncludedMemoryFiles>
				</Event>
				<Event Id="750089663" Name="UI_Menu_Teleport" ObjectPath="\Events\Default Work Unit\UI_Menu_Teleport">
					<IncludedMemoryFiles>
						<File Id="900050537" Language="SFX">
							<ShortName>UI\BAS_Button_Teleport.wav</ShortName>
							<Path>SFX\UI\BAS_Button_Teleport_10C4C929.wem</Path>
						</File>
					</IncludedMemoryFiles>
				</Event>
				<Event Id="3567233235" Name="UI_Quest_Roll_Close" ObjectPath="\Events\Default Work Unit\UI_Quest_Roll_Close">
					<IncludedMemoryFiles>
						<File Id="161770584" Language="SFX">
							<ShortName>UI\BAS_QuestRoll_Close.wav</ShortName>
							<Path>SFX\UI\BAS_QuestRoll_Close_10C4C929.wem</Path>
						</File>
					</IncludedMemoryFiles>
				</Event>
				<Event Id="1399152593" Name="UI_Quest_Roll_Hide" ObjectPath="\Events\Default Work Unit\UI_Quest_Roll_Hide">
					<IncludedMemoryFiles>
						<File Id="288094772" Language="SFX">
							<ShortName>UI\BAS_Inventory_Open.wav</ShortName>
							<Path>SFX\UI\BAS_Inventory_Open_10C4C929.wem</Path>
						</File>
					</IncludedMemoryFiles>
				</Event>
				<Event Id="2702327653" Name="UI_Quest_Roll_Open" ObjectPath="\Events\Default Work Unit\UI_Quest_Roll_Open">
					<IncludedMemoryFiles>
						<File Id="401018015" Language="SFX">
							<ShortName>UI\BAS_QuestRoll_Open.wav</ShortName>
							<Path>SFX\UI\BAS_QuestRoll_Open_10C4C929.wem</Path>
						</File>
					</IncludedMemoryFiles>
				</Event>
				<Event Id="3524454690" Name="UI_Quest_Roll_Show" ObjectPath="\Events\Default Work Unit\UI_Quest_Roll_Show">
					<IncludedMemoryFiles>
						<File Id="288094772" Language="SFX">
							<ShortName>UI\BAS_Inventory_Open.wav</ShortName>
							<Path>SFX\UI\BAS_Inventory_Open_10C4C929.wem</Path>
						</File>
					</IncludedMemoryFiles>
				</Event>
			</IncludedEvents>
			<GameParameters>
				<GameParameter Id="207908541" Name="Time_of_Day" ObjectPath="\Game Parameters\Default Work Unit\Time_of_Day"/>
			</GameParameters>
			<SwitchGroups>
				<SwitchGroup Id="207908541" Name="Time_of_Day" ObjectPath="\Switches\Default Work Unit\Time_of_Day" GUID="{0DB4C265-2556-4FF2-88C0-8853D0EEABBB}">
					<Switches>
						<Switch Id="311764537" Name="Day" ObjectPath="\Switches\Default Work Unit\Time_of_Day\Day" GUID="{12B8D30A-EE92-4CBB-A492-4914DF46DB52}"/>
						<Switch Id="1011622525" Name="Night" ObjectPath="\Switches\Default Work Unit\Time_of_Day\Night" GUID="{23EEB13D-026D-43C2-A3DA-96B33F5888AE}"/>
					</Switches>
				</SwitchGroup>
			</SwitchGroups>
		</SoundBank>
		<SoundBank Id="608898761" Language="SFX" Hash="3782491797">
			<ObjectPath>\SoundBanks\Default Work Unit\Dungeon</ObjectPath>
			<ShortName>Dungeon</ShortName>
			<Path>Dungeon.bnk</Path>
			<IncludedEvents>
				<Event Id="4077685701" Name="Ambient_Region_Dungeon" ObjectPath="\Events\Default Work Unit\Ambient_Region_Dungeon">
					<IncludedMemoryFiles>
						<File Id="765017470" Language="SFX">
							<ShortName>Ambient_Background\BAS_amb_dungeon_day_background_loop_01.wav</ShortName>
							<Path>SFX\Ambient_Background\BAS_amb_dungeon_day_background_loop_01_D79FB2B7.wem</Path>
						</File>
					</IncludedMemoryFiles>
				</Event>
				<Event Id="1999886838" Name="Destruction_Rock_Destroy" ObjectPath="\Events\Default Work Unit\Destruction_Rock_Destroy">
					<IncludedMemoryFiles>
						<File Id="419346019" Language="SFX">
							<ShortName>Destruction\BAS_Destroy_Rock_02.wav</ShortName>
							<Path>SFX\Destruction\BAS_Destroy_Rock_02_10C4C929.wem</Path>
						</File>
						<File Id="629239930" Language="SFX">
							<ShortName>Destruction\BAS_Destroy_Rock_01.wav</ShortName>
							<Path>SFX\Destruction\BAS_Destroy_Rock_01_10C4C929.wem</Path>
						</File>
						<File Id="1008992106" Language="SFX">
							<ShortName>Destruction\BAS_Destroy_Rock_03.wav</ShortName>
							<Path>SFX\Destruction\BAS_Destroy_Rock_03_10C4C929.wem</Path>
						</File>
					</IncludedMemoryFiles>
				</Event>
			</IncludedEvents>
		</SoundBank>
		<SoundBank Id="1355168291" Language="SFX" Hash="864966350">
			<ObjectPath>Init</ObjectPath>
			<ShortName>Init</ShortName>
			<Path>Init.bnk</Path>
			<IncludedAuxBusses>
				<AuxBus Id="243931001" Name="Dungeon_Forge" ObjectPath="\Master-Mixer Hierarchy\Default Work Unit\Master Audio Bus\Dungeon_Forge"/>
				<AuxBus Id="425911480" Name="Dungeon_Library_Statue" ObjectPath="\Master-Mixer Hierarchy\Default Work Unit\Master Audio Bus\Dungeon_Library_Statue"/>
				<AuxBus Id="548199313" Name="Dungeon_MezzanineEntrance" ObjectPath="\Master-Mixer Hierarchy\Default Work Unit\Master Audio Bus\Dungeon_MezzanineEntrance"/>
				<AuxBus Id="567469275" Name="Dungeon_PathToForge" ObjectPath="\Master-Mixer Hierarchy\Default Work Unit\Master Audio Bus\Dungeon_PathToForge"/>
				<AuxBus Id="1156828694" Name="Dungeon_Entrance" ObjectPath="\Master-Mixer Hierarchy\Default Work Unit\Master Audio Bus\Dungeon_Entrance"/>
				<AuxBus Id="1941785149" Name="Dungeon_Library" ObjectPath="\Master-Mixer Hierarchy\Default Work Unit\Master Audio Bus\Dungeon_Library"/>
				<AuxBus Id="2106540524" Name="Dungeon_RoadToCore" ObjectPath="\Master-Mixer Hierarchy\Default Work Unit\Master Audio Bus\Dungeon_RoadToCore"/>
				<AuxBus Id="2213850905" Name="Dungeon_Core" ObjectPath="\Master-Mixer Hierarchy\Default Work Unit\Master Audio Bus\Dungeon_Core"/>
				<AuxBus Id="3352684520" Name="CaveEntrance" ObjectPath="\Master-Mixer Hierarchy\Default Work Unit\Master Audio Bus\CaveEntrance"/>
				<AuxBus Id="4122393694" Name="Cave" ObjectPath="\Master-Mixer Hierarchy\Default Work Unit\Master Audio Bus\Cave"/>
				<AuxBus Id="4158999182" Name="Dungeon_MezzanineRoom" ObjectPath="\Master-Mixer Hierarchy\Default Work Unit\Master Audio Bus\Dungeon_MezzanineRoom"/>
			</IncludedAuxBusses>
			<GameParameters>
				<GameParameter Id="1333239961" Name="MenuSlider_Master_Volume" ObjectPath="\Game Parameters\Default Work Unit\MenuSlider_Master_Volume"/>
				<GameParameter Id="2642438544" Name="MenuSlider_Music_Volume" ObjectPath="\Game Parameters\Default Work Unit\MenuSlider_Music_Volume"/>
			</GameParameters>
		</SoundBank>
		<SoundBank Id="1421251628" Language="SFX" Hash="222163245">
			<ObjectPath>\SoundBanks\Default Work Unit\Woodlands</ObjectPath>
			<ShortName>Woodlands</ShortName>
			<Path>Woodlands.bnk</Path>
			<IncludedEvents>
				<Event Id="1049266392" Name="Ambient_Region_Woodlands" ObjectPath="\Events\Default Work Unit\Ambient_Region_Woodlands">
					<IncludedMemoryFiles>
						<File Id="1069939439" Language="SFX">
							<ShortName>Ambient_Background\BAS_amb_forest_day_background_loop_01.wav</ShortName>
							<Path>SFX\Ambient_Background\BAS_amb_forest_day_background_loop_01_9CDB22D5.wem</Path>
						</File>
					</IncludedMemoryFiles>
				</Event>
				<Event Id="1934835592" Name="Ambient_Waterfall" ObjectPath="\Events\Default Work Unit\Ambient_Waterfall">
					<IncludedMemoryFiles>
						<File Id="152023859" Language="SFX">
							<ShortName>Ambient_Emitters\BAS_Waterfall.wav</ShortName>
							<Path>SFX\Ambient_Emitters\BAS_Waterfall_D79FB2B7.wem</Path>
						</File>
					</IncludedMemoryFiles>
				</Event>
			</IncludedEvents>
			<GameParameters>
				<GameParameter Id="207908541" Name="Time_of_Day" ObjectPath="\Game Parameters\Default Work Unit\Time_of_Day"/>
			</GameParameters>
			<SwitchGroups>
				<SwitchGroup Id="207908541" Name="Time_of_Day" ObjectPath="\Switches\Default Work Unit\Time_of_Day" GUID="{0DB4C265-2556-4FF2-88C0-8853D0EEABBB}">
					<Switches>
						<Switch Id="311764537" Name="Day" ObjectPath="\Switches\Default Work Unit\Time_of_Day\Day" GUID="{12B8D30A-EE92-4CBB-A492-4914DF46DB52}"/>
						<Switch Id="1011622525" Name="Night" ObjectPath="\Switches\Default Work Unit\Time_of_Day\Night" GUID="{23EEB13D-026D-43C2-A3DA-96B33F5888AE}"/>
					</Switches>
				</SwitchGroup>
			</SwitchGroups>
		</SoundBank>
		<SoundBank Id="1850388778" Language="SFX" Hash="841097894">
			<ObjectPath>\SoundBanks\Default Work Unit\Desert</ObjectPath>
			<ShortName>Desert</ShortName>
			<Path>Desert.bnk</Path>
			<IncludedEvents>
				<Event Id="3408705206" Name="Ambient_Region_Desert" ObjectPath="\Events\Default Work Unit\Ambient_Region_Desert">
					<IncludedMemoryFiles>
						<File Id="238742817" Language="SFX">
							<ShortName>Ambient_Background\BAS_amb_desert_day_background_loop_01.wav</ShortName>
							<Path>SFX\Ambient_Background\BAS_amb_desert_day_background_loop_01_D79FB2B7.wem</Path>
						</File>
						<File Id="893374816" Language="SFX">
							<ShortName>Ambient_Background\BAS_amb_desert_night_background_loop_01.wav</ShortName>
							<Path>SFX\Ambient_Background\BAS_amb_desert_night_background_loop_01_D79FB2B7.wem</Path>
						</File>
					</IncludedMemoryFiles>
					<DefaultSwitchValue>{12B8D30A-EE92-4CBB-A492-4914DF46DB52}</DefaultSwitchValue>
					<SwitchContainers>
						<SwitchContainer SwitchValue="{12B8D30A-EE92-4CBB-A492-4914DF46DB52}">
							<Media>
								<File Id="238742817"/>
							</Media>
						</SwitchContainer>
						<SwitchContainer SwitchValue="{23EEB13D-026D-43C2-A3DA-96B33F5888AE}">
							<Media>
								<File Id="893374816"/>
							</Media>
						</SwitchContainer>
					</SwitchContainers>
				</Event>
				<Event Id="578570680" Name="Destruction_Volcanic_Boulder_Impact" ObjectPath="\Events\Default Work Unit\Destruction_Volcanic_Boulder_Impact">
					<IncludedMemoryFiles>
						<File Id="285808865" Language="SFX">
							<ShortName>Destruction\Volcanic Boulder\DebrisDirt.wav</ShortName>
							<Path>SFX\Destruction\Volcanic Boulder\DebrisDirt_10C4C929.wem</Path>
						</File>
						<File Id="337745466" Language="SFX">
							<ShortName>Destruction\Volcanic Boulder\Explosion.wav</ShortName>
							<Path>SFX\Destruction\Volcanic Boulder\Explosion_10C4C929.wem</Path>
						</File>
					</IncludedMemoryFiles>
				</Event>
			</IncludedEvents>
			<GameParameters>
				<GameParameter Id="207908541" Name="Time_of_Day" ObjectPath="\Game Parameters\Default Work Unit\Time_of_Day"/>
			</GameParameters>
			<SwitchGroups>
				<SwitchGroup Id="207908541" Name="Time_of_Day" ObjectPath="\Switches\Default Work Unit\Time_of_Day" GUID="{0DB4C265-2556-4FF2-88C0-8853D0EEABBB}">
					<Switches>
						<Switch Id="311764537" Name="Day" ObjectPath="\Switches\Default Work Unit\Time_of_Day\Day" GUID="{12B8D30A-EE92-4CBB-A492-4914DF46DB52}"/>
						<Switch Id="1011622525" Name="Night" ObjectPath="\Switches\Default Work Unit\Time_of_Day\Night" GUID="{23EEB13D-026D-43C2-A3DA-96B33F5888AE}"/>
					</Switches>
				</SwitchGroup>
			</SwitchGroups>
		</SoundBank>
		<SoundBank Id="2201105581" Language="SFX" Hash="1351233711">
			<ObjectPath>\SoundBanks\Default Work Unit\Credits</ObjectPath>
			<ShortName>Credits</ShortName>
			<Path>Credits.bnk</Path>
			<IncludedEvents>
				<Event Id="1882971781" Name="Music_Credits" ObjectPath="\Events\Default Work Unit\Music_Credits">
					<IncludedMemoryFiles>
						<File Id="24588650" Language="SFX">
							<ShortName>Music\Credits_120BPM_4_4_L8M_P0.wav</ShortName>
							<Path>SFX\Music\Credits_120BPM_4_4_L8M_P0_45E3A7F1.wem</Path>
						</File>
					</IncludedMemoryFiles>
				</Event>
			</IncludedEvents>
		</SoundBank>
		<SoundBank Id="2482365692" Language="SFX" Hash="3111016227">
			<ObjectPath>\SoundBanks\Default Work Unit\PineForest</ObjectPath>
			<ShortName>PineForest</ShortName>
			<Path>PineForest.bnk</Path>
			<IncludedEvents>
				<Event Id="808171864" Name="Ambient_Region_PineForest" ObjectPath="\Events\Default Work Unit\Ambient_Region_PineForest">
					<IncludedMemoryFiles>
						<File Id="103404229" Language="SFX">
							<ShortName>Ambient_Background\BAS_amb_pineforest_night_background_loop_01.wav</ShortName>
							<Path>SFX\Ambient_Background\BAS_amb_pineforest_night_background_loop_01_4117AE9A.wem</Path>
						</File>
					</IncludedMemoryFiles>
				</Event>
			</IncludedEvents>
		</SoundBank>
		<SoundBank Id="3945572659" Language="SFX" Hash="1944262989">
			<ObjectPath>\SoundBanks\Default Work Unit\Village</ObjectPath>
			<ShortName>Village</ShortName>
			<Path>Village.bnk</Path>
			<IncludedEvents>
				<Event Id="2752753183" Name="Ambient_Region_Village" ObjectPath="\Events\Default Work Unit\Ambient_Region_Village">
					<IncludedMemoryFiles>
						<File Id="198421452" Language="SFX">
							<ShortName>Ambient_Background\BAS_amb_village_day_background_loop_01.wav</ShortName>
							<Path>SFX\Ambient_Background\BAS_amb_village_day_background_loop_01_327512D8.wem</Path>
						</File>
						<File Id="522645543" Language="SFX">
							<ShortName>Ambient_Background\BAS_amb_village_night_background_loop_01.wav</ShortName>
							<Path>SFX\Ambient_Background\BAS_amb_village_night_background_loop_01_522AE39A.wem</Path>
						</File>
					</IncludedMemoryFiles>
					<DefaultSwitchValue>{12B8D30A-EE92-4CBB-A492-4914DF46DB52}</DefaultSwitchValue>
					<SwitchContainers>
						<SwitchContainer SwitchValue="{12B8D30A-EE92-4CBB-A492-4914DF46DB52}">
							<Media>
								<File Id="198421452"/>
							</Media>
						</SwitchContainer>
						<SwitchContainer SwitchValue="{23EEB13D-026D-43C2-A3DA-96B33F5888AE}">
							<Media>
								<File Id="522645543"/>
							</Media>
						</SwitchContainer>
					</SwitchContainers>
				</Event>
				<Event Id="2258053876" Name="Ambient_River" ObjectPath="\Events\Default Work Unit\Ambient_River">
					<IncludedMemoryFiles>
						<File Id="18508739" Language="SFX">
							<ShortName>Ambient_Emitters\BAS_Water_River.wav</ShortName>
							<Path>SFX\Ambient_Emitters\BAS_Water_River_D79FB2B7.wem</Path>
						</File>
					</IncludedMemoryFiles>
				</Event>
				<Event Id="2208964750" Name="Ambient_Windmill" ObjectPath="\Events\Default Work Unit\Ambient_Windmill">
					<IncludedMemoryFiles>
						<File Id="200344808" Language="SFX">
							<ShortName>Ambient_Emitters\BAS_WindMillBlade_03.wav</ShortName>
							<Path>SFX\Ambient_Emitters\BAS_WindMillBlade_03_10C4C929.wem</Path>
						</File>
						<File Id="253068894" Language="SFX">
							<ShortName>Ambient_Emitters\BAS_WindMillBlade_01.wav</ShortName>
							<Path>SFX\Ambient_Emitters\BAS_WindMillBlade_01_ACF58286.wem</Path>
						</File>
						<File Id="702538557" Language="SFX">
							<ShortName>Ambient_Emitters\BAS_WindMillBlade_02.wav</ShortName>
							<Path>SFX\Ambient_Emitters\BAS_WindMillBlade_02_10C4C929.wem</Path>
						</File>
					</IncludedMemoryFiles>
				</Event>
			</IncludedEvents>
			<GameParameters>
				<GameParameter Id="207908541" Name="Time_of_Day" ObjectPath="\Game Parameters\Default Work Unit\Time_of_Day"/>
			</GameParameters>
			<SwitchGroups>
				<SwitchGroup Id="207908541" Name="Time_of_Day" ObjectPath="\Switches\Default Work Unit\Time_of_Day" GUID="{0DB4C265-2556-4FF2-88C0-8853D0EEABBB}">
					<Switches>
						<Switch Id="311764537" Name="Day" ObjectPath="\Switches\Default Work Unit\Time_of_Day\Day" GUID="{12B8D30A-EE92-4CBB-A492-4914DF46DB52}"/>
						<Switch Id="1011622525" Name="Night" ObjectPath="\Switches\Default Work Unit\Time_of_Day\Night" GUID="{23EEB13D-026D-43C2-A3DA-96B33F5888AE}"/>
					</Switches>
				</SwitchGroup>
			</SwitchGroups>
		</SoundBank>
		<SoundBank Id="4122393694" Language="SFX" Hash="4096307126">
			<ObjectPath>\SoundBanks\Default Work Unit\Cave</ObjectPath>
			<ShortName>Cave</ShortName>
			<Path>Cave.bnk</Path>
			<IncludedEvents>
				<Event Id="1331382810" Name="Ambient_Region_Cave" ObjectPath="\Events\Default Work Unit\Ambient_Region_Cave">
					<IncludedMemoryFiles>
						<File Id="578142134" Language="SFX">
							<ShortName>Ambient_Background\BAS_amb_cave_background_LP.wav</ShortName>
							<Path>SFX\Ambient_Background\BAS_amb_cave_background_LP_D79FB2B7.wem</Path>
						</File>
					</IncludedMemoryFiles>
				</Event>
				<Event Id="2644063196" Name="Ambient_WaterDrop" ObjectPath="\Events\Default Work Unit\Ambient_WaterDrop">
					<IncludedMemoryFiles>
						<File Id="251067468" Language="SFX">
							<ShortName>Ambient_Emitters\BAS_WaterDrops_02.wav</ShortName>
							<Path>SFX\Ambient_Emitters\BAS_WaterDrops_02_10C4C929.wem</Path>
						</File>
						<File Id="294056133" Language="SFX">
							<ShortName>Ambient_Emitters\BAS_WaterDrops_05.wav</ShortName>
							<Path>SFX\Ambient_Emitters\BAS_WaterDrops_05_10C4C929.wem</Path>
						</File>
						<File Id="726968632" Language="SFX">
							<ShortName>Ambient_Emitters\BAS_WaterDrops_01.wav</ShortName>
							<Path>SFX\Ambient_Emitters\BAS_WaterDrops_01_10C4C929.wem</Path>
						</File>
						<File Id="770635657" Language="SFX">
							<ShortName>Ambient_Emitters\BAS_WaterDrops_03.wav</ShortName>
							<Path>SFX\Ambient_Emitters\BAS_WaterDrops_03_10C4C929.wem</Path>
						</File>
						<File Id="1030438884" Language="SFX">
							<ShortName>Ambient_Emitters\BAS_WaterDrops_04.wav</ShortName>
							<Path>SFX\Ambient_Emitters\BAS_WaterDrops_04_10C4C929.wem</Path>
						</File>
						<File Id="1065114496" Language="SFX">
							<ShortName>Ambient_Emitters\BAS_WaterDrops_06.wav</ShortName>
							<Path>SFX\Ambient_Emitters\BAS_WaterDrops_06_10C4C929.wem</Path>
						</File>
					</IncludedMemoryFiles>
				</Event>
				<Event Id="448719855" Name="Destruction_Crystal_Destroy" ObjectPath="\Events\Default Work Unit\Destruction_Crystal_Destroy">
					<IncludedMemoryFiles>
						<File Id="249237975" Language="SFX">
							<ShortName>Destruction\BAS_Crystals_Destroy.wav</ShortName>
							<Path>SFX\Destruction\BAS_Crystals_Destroy_10C4C929.wem</Path>
						</File>
					</IncludedMemoryFiles>
				</Event>
			</IncludedEvents>
		</SoundBank>
	</SoundBanks>
</SoundBanksInfo>
